Workbook
Name arp: #REF!
Name arp: #REF!
Name arp: #REF!
Name Riesgo: #REF!
Name Riesgo: #REF!
Name Riesgo: #REF!

Sheet PLATOS
C1: TALLER COSTOS
C2: VERSIÓN 3
C3: 44802
C4: ALMA RURAL
A5: INICIA EL DIA EN EL CAMPO | C5: COSTO | D5: PRECIO DE VENTA | E5: % DE COSTO
A6: 1 | B6: =+'ESTANDAR CAMPO'!A1 -> CAMPESINO | C6: =+'ESTANDAR CAMPO'!F14 -> 10492.311 | D6: 33000 | E6: =+C6/D6 -> 0.31794883
A7: =1+A6 -> 2 | B7: HUEVOS EN CACEROLA | C7: =+'ESTANDAR CAMPO'!F40 -> 5599.4442 | D7: 24000 | E7: =+C7/D7 -> 0.23331017
A8: =1+A7 -> 3 | B8: HUEVOS NAPOLITANOS | C8: =+'ESTANDAR CAMPO'!F66 -> 10381.882 | D8: 24000 | E8: =+C8/D8 -> 0.4325784
A9: =1+A8 -> 4 | B9: HUEVOS AL GUSTO | C9: =+'ESTANDAR CAMPO'!F92 -> 6606.1867 | D9: 25000 | E9: =+C9/D9 -> 0.26424747
A10: =1+A9 -> 5 | B10: OMELETTE | C10: =+'ESTANDAR CAMPO'!F92 -> 6606.1867 | D10: 28000 | E10: =+C10/D10 -> 0.23593524
A12: DESAYUNOS SALUABLES | C12: COSTO | D12: COSTO MAX | E12: % DE COSTO
A13: 6 | B13: BOWL NUTRITIVO | C13: =+'ESTANDAR SALUDABLE'!F11 -> 8428.4 | D13: 20000 | E13: =+C13/D13 -> 0.42142
A14: =1+A13 -> 7 | B14: WAFFLE | C14: =+'ESTANDAR SALUDABLE'!F34 -> 12612.755 | D14: 20000 | E14: =+C14/D14 -> 0.63063775
A15: =1+A14 -> 8 | B15: BATIDO VERDE | C15: =+'ESTANDAR SALUDABLE'!F53 -> 5247 | D15: 15000 | E15: =+C15/D15 -> 0.3498
A17: ENTRADAS DE LA HUERTA | C17: COSTO | D17: COSTO MAX | E17: % DE COSTO
A18: 9 | B18: PATACONAS DE LAS MONTAÑAS COLOMBIANAS | C18: =+'ESTANDAR ENTRADAS'!F10 -> 8117.3731 | D18: 14000 | E18: =+C18/D18 -> 0.57981236
A19: =1+A18 -> 10 | B19: DULCE TENTACIÓN ABORRAJADA | C19: =+'ESTANDAR ENTRADAS'!F31 -> 4219.1 | D19: 20000 | E19: =+C19/D19 -> 0.210955
A20: =1+A19 -> 11 | B20: CHICHARRON CAMPESINO | C20: =+'ESTANDAR ENTRADAS'!F58 -> 20268.461 | D20: 28000 | E20: =+C20/D20 -> 0.72387362 | F20: REVISAR VALORES DE RECETA
A22: AVES DEL CORRAL | C22: COSTO | D22: COSTO MAX | E22: % DE COSTO
A23: 12 | B23: BROCHETAS DE POLLO A LA BRASA | C23: =+'AVES DEL CORRAL'!F12 -> 13392.241 | D23: 30000 | E23: =+C23/D23 -> 0.44640803
A24: =1+A23 -> 13 | B24: POLLO CRIOLLO SALTEADO | C24: =+'AVES DEL CORRAL'!F37 -> 14436.711 | D24: 38000 | E24: =+C24/D24 -> 0.37991344
A25: =1+A24 -> 14 | B25: PECHUGA DE POLLO A LA PARRILLA | C25: =+'AVES DEL CORRAL'!F60 -> 13150.881 | D25: 34000 | E25: =+C25/D25 -> 0.38679062
A26: =1+A25 -> 15 | B26: PECHUGA DE POLLO EN SALSA DE CHAMPIÑONES | C26: =+'AVES DEL CORRAL'!F84 -> 16649.607 | D26: 38000 | E26: =+C26/D26 -> 0.43814755
A28: SABORES DEL CERDO | C28: COSTO | D28: PRECIO DE VENTA | E28: % DE COSTO
A29: 16 | B29: COSTILLAS DE CERDO BBQ | C29: =+'SABORES DE CERDO'!F15 -> 15004.539 | D29: 40000 | E29: 0.38
A31: TESOROS DEL RIO | C31: COSTO | D31: PRECIO DE VENTA | E31: % DE COSTO
A32: 17 | B32: TRUCHA AHUMADA DE LA HUERTA | C32: =+'TESOROS DEL RIO'!F18 -> 16193.544 | D32: 38000 | E32: =+C32/D32 -> 0.42614591
A33: =+A32+1 -> 18 | B33: TRUCHA A LA CRIOLLA | C33: =+'TESOROS DEL RIO'!F44 -> 17423.273 | D33: 39000 | E33: =+C33/D33 -> 0.44675059
A34: =+A33+1 -> 19 | B34: TRUCHA CON CHAMPIÑONES | C34: =+'TESOROS DEL RIO'!F70 -> 15260.446 | D34: 42000 | E34: =+C34/D34 -> 0.36334396
A35: =+A34+1 -> 20 | B35: TRUCHA AL AJILLO | C35: =+'TESOROS DEL RIO'!F98 -> 18707.759 | D35: 40000 | E35: =+C35/D35 -> 0.46769398
A36: =+A35+1 -> 21 | B36: TRUCHA CON ALMENDRAS | C36: =+'TESOROS DEL RIO'!F126 -> 20083.359 | D36: 43000 | E36: =+C36/D36 -> 0.46705486
A37: =+A36+1 -> 22 | B37: TRUCHA DE COCO | C37: =+'TESOROS DEL RIO'!F155 -> 22267.546 | D37: 45000 | E37: =+C37/D37 -> 0.49483434
A38: =+A37+1 -> 23 | B38: TRUCHA TROPICAL | C38: =+'TESOROS DEL RIO'!F185 -> 25039.142 | D38: 45000 | E38: =+C38/D38 -> 0.55642538
A40: CARNES DEL CORRAL | C40: COSTO | D40: PRECIO DE VENTA | E40: % DE COSTO
A41: 24 | B41: CHURRASCO DE RES | C41: =+'CARNE DEL CORRAL'!F15 -> 20567.197 | D41: 43000 | E41: =+C41/D41 -> 0.4783069
A42: =+A41+1 -> 25 | B42: PUNTA DE ANCA ASADA | C42: =+'CARNE DEL CORRAL'!F40 -> 22333.432 | D42: 44000 | E42: =+C42/D42 -> 0.507578
A43: =+A42+1 -> 26 | B43: CORDERO AHUMADO | C43: =+'CARNE DEL CORRAL'!F68 -> 5006.5554 | D43: 60000 | E43: =+C43/D43 -> 0.083442591 | F43: FALTAN INGREDIENTES
A44: =+A43+1 -> 27 | B44: HAMBURGUESA ARTESANAL DE LA CASA | C44: =+'CARNE DEL CORRAL'!F94 -> 10498.627 | D44: 29000 | E44: =+C44/D44 -> 0.36202164
A45: =+A44+1 -> 28 | B45: HAMBURGUESA ANGUS PREMIUM | C45: =+'CARNE DEL CORRAL'!F122 -> 6744.774 | D45: 38000 | E45: =+C45/D45 -> 0.17749405 | F45: FALTAN INGREDIENTES
A46: =+A45+1 -> 29 | B46: HAMBURGUESA DE CORDERO | C46: =+'CARNE DEL CORRAL'!F148 -> 6744.774 | D46: 38000 | E46: =+C46/D46 -> 0.17749405 | F46: FALTAN INGREDIENTES
A48: OPCIÓN VEGETARIANA | C48: COSTO | D48: PRECIO DE VENTA | E48: % DE COSTO
A49: 30 | B49: RAVIOLIS DE CHAMPIÑONES | C49: =+VEGETARIANOS!F15 -> 8163.1263 | D49: 36000 | E49: =+C49/D49 -> 0.22675351
A50: =+A49+1 -> 31 | B50: BOWL VEGANO | C50: =+VEGETARIANOS!F38 -> 4610 | D50: 33000
A52: MENÚ INFANTIL | C52: COSTO | D52: PRECIO DE VENTA | E52: % DE COSTO
A53: 32 | B53: POLLO INFANTIL CON QUINUA | C53: =+VEGETARIANOS!F60 -> 10126.208 | D53: 28000 | E53: =+C53/D53 -> 0.36165029

Sheet LISTA MAESTRA
C1: TALLER COSTOS
C2: VERSIÓN 3 | G2: UNIDADES DE MEDIDA | H2: SIMBOLO
C3: 44802 | G3: GRAMOS | H3: GR | I3: UNIDADES DE MEDIDA PARA PESO
C4: ALMA RURAL | G4: LIBRAS | H4: LB
A5: CARNES ROJAS | B5: UND/M | C5: PRECIO COMPRA | D5: COSTO GR | E5: V/ PORCIÓN | G5: KILOGRAMOS | H5: KL
A6: PUNTA DE ANCA | B6: KL | C6: 48800 | D6: =+C6/1000 -> 48.8 | G6: CENTIMETROS CUBICOS | H6: CC | I6: UNIDADES DE MEDIDA PARA VOLUMEN
A7: LOMO ANCHO | B7: KL | C7: 44000 | D7: =+C7/1000 -> 44 | G7: LITROS | H7: LTS
A8: MURILLO PIERNA | B8: KL | C8: 23600 | D8: =+C8/1000 -> 23.6 | G8: UNIDADES | H8: UND | I8: VALOR INDIVIDUAL
A9: HUESO DE COGOTE | B9: KL | C9: 10710 | D9: =+C9/1000 -> 10.71
A10: PECHO KILO | B10: KL | C10: 27600 | D10: =+C10/1000 -> 27.6
A11: MORRILLO KILO | B11: KL | C11: 24000 | D11: =+C11/1000 -> 24
A13: PESCADOS Y MARISCOS | B13: UND/M | C13: PRECIO COMPRA | D13: COSTO und | E13: V/ PORCIÓN
A14: TRUCHA | B14: KL | C14: 229680 | D14: =+C14/20 -> 11484
A15: CAMARON CRUDO | B15: UND | C15: 850 | D15: =+C15/1 -> 850
A20: CERDO | B20: UND/M | C20: PRECIO COMPRA | D20: COSTO GR | E20: V/ PORCIÓN
A21: COSTILLA DE CERDO | B21: KL | C21: 23600 | D21: =+C21/1000 -> 23.6
A22: TOCINO BARRIGUERO | B22: KL | C22: 22000 | D22: =+C22/1000 -> 22
A23: TOCINO CARNUDO | B23: KL | C23: 28000 | D23: =+C23/1000 -> 28
A24: PAPADA | B24: KL | C24: 19000 | D24: =+C24/1000 -> 19
A25: JAMON RICA | B25: GR | C25: 8400 | D25: =+C25/15 -> 560
A26: PERNIL CERDO | B26: GR | C26: 23600 | D26: =+C26/1000 -> 23.6
A27: TOCINETA AHUMADA X250 | B27: GR | C27: 6600 | D27: =+C27/10 -> 660
A29: POLLO | B29: UND/M | C29: PRECIO COMPRA | D29: COSTO GR | E29: V/ PORCIÓN
A30: PECHUGA DE POLLO | B30: KL | C30: 23400 | D30: =+C30/1000 -> 23.4
A31: ALAS DE POLLO | B31: KL | C31: 16400 | D31: =+C31/1000 -> 16.4
A32: VERDURAS | B32: UND/M | C32: PRECIO COMPRA | D32: COSTO GR | E32: V/ PORCIÓN
A33: MAZORCA CHOCLO | B33: GR | C33: 6500 | D33: =+C33/1000 -> 6.5
A34: PAPA CRIOLLA | B34: GR | C34: 6800 | D34: =+C34/1000 -> 6.8
A35: YUCA | B35: GR | C35: 5700 | D35: =+C35/1000 -> 5.7
A36: LECHUGA BATAVIA | B36: GR | C36: 2200 | D36: =+C36/250 -> 8.8
A37: AGUACATE | B37: GR | C37: 12000 | D37: =+C37/1000 -> 12
A38: AREPAS PQT X 10 | B38: UN | C38: 1000 | D38: =+C38/10 -> 100
A39: HUEVO AA | B39: UND | C39: 13000 | D39: =+C39/30 -> 433.33333
A40: CHAMPIÑON | B40: GR | C40: 14800 | D40: =+C40/500 -> 29.6
A41: ESPINACA | B41: GR | C41: 3400 | D41: =+C41/200 -> 17
A42: APIO | B42: ATADO | C42: 3000 | D42: =+C42/250 -> 12
A43: PAPA PASTUSA | B43: KL | C43: 2900 | D43: =+C43/1000 -> 2.9
A44: MALLA DE AJO | B44: 125 | C44: 1100 | D44: =+C44/50 -> 22
A45: CEBOLLA LARGA | B45: LB | C45: 3400 | D45: =+C45/500 -> 6.8
A46: TOMATE CHONTO | B46: KL | C46: 3200 | D46: =+C46/1000 -> 3.2
A47: LIMON | B47: KL | C47: 5700 | D47: =+C47/1000 -> 5.7
A48: CEBOLLA CABEZONA BLANCA | B48: KL | C48: 3700 | D48: =+C48/1000 -> 3.7
A49: CEBOLLA CABEZONA ROJA | B49: KL | C49: 4600 | D49: =+C49/1000 -> 4.6
A50: MANZANA VERDE | B50: UND | C50: 2600 | D50: =+C50/1 -> 2600
A51: PEPINO COHOMBRO | B51: KL | C51: 3700 | D51: =+C51/1000 -> 3.7
A52: PIÑA ORO MIEL | B52: KL | C52: 3500 | D52: =+C52/1000 -> 3.5
A53: BANANO | B53: KL | C53: 3200 | D53: =+C53/1000 -> 3.2
A54: FRESA | B54: 250 | C54: 5500 | D54: =+C54/250 -> 22
A55: LULO | B55: KL | C55: 6500 | D55: =+C55/1000 -> 6.5
A56: ZANAHORIA | B56: KL | C56: 5900 | D56: =+C56/1000 -> 5.9
A57: MANGO | B57: KL | C57: 5800 | D57: =+C57/1000 -> 5.8
A58: REPOLLO MORADO | B58: KL | C58: 7800 | D58: =+C58/1000 -> 7.8
A59: PLATANO VERDE | B59: KL | C59: 7000 | D59: =+C59/1000 -> 7
A60: PIMENTON | B60: KL | C60: 10600 | D60: =+C60/1000 -> 10.6
A61: HIERBAS Y ESPECIAS | B61: UND/M | C61: PRECIO COMPRA | D61: COSTO GR | E61: V/ PORCIÓN
A62: CILANTRO ATADO | B62: GR | C62: 1700 | D62: =+C62/500 -> 3.4
A63: CILANTRON MONIK | B63: GR | C63: 1550 | D63: =+C63/30 -> 51.666667
A64: CANELA | B64: GR | C64: 4100 | D64: =+C64/20 -> 205
A65: CLAVOS | B65: GR | C65: 1400 | D65: =+C65/10 -> 140
A66: LAUREL | B66: GR | C66: 6400 | D66: =+C66/5.67 -> 1128.7478
A67: TOMILLO | B67: GR | C67: 800 | D67: =+C67/10 -> 80
A68: ROMERO | B68: GR | C68: 1250 | D68: =+C68/10 -> 125
A69: CURRY | B69: GR | C69: 2100 | D69: =+C69/20 -> 105
A71: LACTEOS Y DERIVADOS | B71: UND/M | C71: PRECIO COMPRA | D71: COSTO GR | E71: V/ PORCIÓN
A72: LECHE MERCACENTRO X 1000 CC | B72: CC | C72: 3650 | D72: =+C72/1000 -> 3.65
A73: CREMA DE LECHE COLANTA | B73: GR | C73: 17600 | D73: =+C73/870 -> 20.229885
A74: QUESO CRIOLLO | B74: LB | C74: 11700 | D74: =+C74/500 -> 23.4
A75: CREMA DE COCO | B75: GR | C75: 16100 | D75: =+C75/400 -> 40.25
A76: YOGURTH TARRITO | B76: UNIDAD | C76: 2500 | D76: =+C76/1 -> 2500
A79: ENCURTIDOS Y SALSAS | B79: UND/M | C79: PRECIO COMPRA | D79: COSTO GR | E79: V/ PORCIÓN
A80: VINAGRE | B80: CC | C80: 6300 | D80: =+C80/1000 -> 6.3
A81: PEPINILLOS | B81: GR | C81: 6100 | D81: =+C81/250 -> 24.4
A84: ABARROTES Y OTROS | B84: UND/M | C84: PRECIO COMPRA | D84: COSTO GR | E84: V/ PORCIÓN
A85: CHUCULA TOCAIMA 500 GR | B85: GR | C85: 3700 | D85: =+C85/500 -> 7.4
A86: PANELA CUADRO | B86: GR | C86: 6600 | D86: =+C86/1000 -> 6.6
A87: MARGARINA RAMMA BALDE * 4 KL | B87: KL | C87: 69050 | D87: =+C87/4000 -> 17.2625
A88: CHIP DE CHOCOLATE 1/2 | B88: GR | C88: 10602 | D88: =+C88/250 -> 42.408
A89: ALMIYUCA | B89: KL | C89: 4000 | D89: =+C89/1000 -> 4
A90: ACEITE GIRASOL | B90: CC | C90: 22500 | D90: =+C90/2000 -> 11.25
A91: ARROZ DIANA PREMIUM | B91: GR | C91: 3200 | D91: =+C91/500 -> 6.4
A92: AZUCAR MERCACENTRO | B92: GR | C92: 11250 | D92: =+C92/2500 -> 4.5
A93: FRIJOL CARGAMANTO | B93: GR | C93: 5450 | D93: =+C93/500 -> 10.9
A94: QUINUA PEPA | B94: GR | C94: 16900 | D94: =+C94/500 -> 33.8
A95: SAL | B95: KL | C95: 7400 | D95: =+C95/3000 -> 2.4666667
A96: HARINA DE TRIGO | B96: LB | C96: 1700 | D96: =+C96/500 -> 3.4
A97: HARINA DE YUCA | B97: GR | C97: 11700 | D97: =+C97/300 -> 39
A98: POLVO DE HORNEAR | B98: GR | C98: 1900 | D98: =+C98/20 -> 95
A99: PEPRON CHINO | B99: GR | C99: 6800 | D99: =+C99/50 -> 136
A100: HOJA DE PLATANO | B100: PQT | C100: 4500 | D100: =+C100/20 -> 225
A101: PASTILLA DE CHOCOLATE | B101: GR | C101: 7900 | D101: =+C101/16 -> 493.75
A102: ACEITE BIDON | B102: GR | C102: 99200 | D102: =+C102/10000 -> 9.92
A103: SODA | B103: UND | C103: 2500 | D103: =+C103/1 -> 2500
A104: PALOS DE PINCHO | B104: UND | C104: 7818 | D104: =+C104/100 -> 78.18
A105: SAL PARRILLERA | B105: GR | C105: 10700 | D105: =+C105/380 -> 28.157895
A106: CUERDA | B106: CM
A107: PIMIENTA MOLID | B107: GR | C107: 6400 | D107: =+C107/20 -> 320
A108: CERVEZA | B108: UND | C108: 40200 | D108: =+C108/12 -> 3350
A109: SALSA SOYA | B109: LT | C109: 6400 | D109: =+C109/1000 -> 6.4
A110: SALSA INGLESA | B110: CC | C110: 5400 | D110: =+C110/180 -> 30
A111: BIZCOCHOS | B111: UND | C111: 10820 | D111: =+C111/50 -> 216.4
...

Sheet RECETA BASE
A1: CALDO DE ALAS
A2: RECETAS ESTANDAR ALMA RURAL 2025
E3: RECETA # | F3: 1
E4: # PORCIONES | F4: 1
A5: COD. | B5: INGREDIENTES | C5: UNID | D5: CANT. | E5: V/UNIT. | F5: V/TOTAL
B6: ALAS | C6: UND | D6: 1 | E6: =+'LISTA MAESTRA'!D31 -> 16.4 | F6: =E6*D6 -> 16.4
B7: PAPA CRIOLLA | C7: GR | D7: 150 | E7: =+'LISTA MAESTRA'!D34 -> 6.8 | F7: =E7*D7 -> 1020
B8: PAPA PASTUSA | C8: UND | D8: 200 | E8: =+'LISTA MAESTRA'!D43 -> 2.9 | F8: =E8*D8 -> 580
B9: CILANTRO | C9: GR | D9: 10 | E9: =+'LISTA MAESTRA'!D62 -> 3.4 | F9: =E9*D9 -> 34
B10: AJO | C10: GR | D10: 2 | E10: =+'LISTA MAESTRA'!D44 -> 22 | F10: =E10*D10 -> 44
B11: SAL | C11: GR | D11: 2 | E11: =+'LISTA MAESTRA'!D95 -> 2.4666667 | F11: =E11*D11 -> 4.9333333
B12: CILANTRON | C12: GR | D12: 10 | E12: =+'LISTA MAESTRA'!D63 -> 51.666667 | F12: =E12*D12 -> 516.66667
A14: COSTO TOTAL DE LOS INGREDIENTES | F14: =SUM(F6:F13) -> 2216
A15: MARGEN DE ERROR O VARIACIÓN | E15: 0.06 | F15: =+F14*E15 -> 132.96
A16: COSTO DE UNA PORCION + EL MARGEN DE ERROR | F16: =+F14+F15 -> 2348.96
A17: COSTO TOTAL DE UNA PORCION | F17: =+F14/F4 -> 2216
A18: COSTO TOTAL DE LOS INGREDIENTES | F18: =ROUND(F17, -2) -> 2200
A21: HUEVOS CRIOLLOS
A22: RECETAS ESTANDAR ALMA RURAL 2025
E23: RECETA # | F23: 2
E24: # PORCIONES | F24: 1
A25: COD. | B25: INGREDIENTES | C25: UNID | D25: CANT. | E25: V/UNIT. | F25: V/TOTAL
B26: HUEVO | C26: UND | D26: 2 | E26: =+'LISTA MAESTRA'!D39 -> 433.33333 | F26: =E26*D26 -> 866.66667
B27: CEBOLLA LARGA | C27: GR | D27: 20 | E27: =+'LISTA MAESTRA'!D45 -> 6.8 | F27: =E27*D27 -> 136
B28: TOMATE CHONTO | C28: GR | D28: 150 | E28: =+'LISTA MAESTRA'!D46 -> 3.2 | F28: =E28*D28 -> 480
B29: MARGARINA | C29: GR | D29: 60 | E29: =+'LISTA MAESTRA'!D87 -> 17.2625 | F29: =E29*D29 -> 1035.75
B30: SAL | C30: GR | D30: 1 | E30: =+'LISTA MAESTRA'!D95 -> 2.4666667 | F30: =E30*D30 -> 2.4666667
F31: =E31*D31 -> 0
A32: COSTO TOTAL DE LOS INGREDIENTES | F32: =SUM(F26:F31) -> 2520.8833
A33: MARGEN DE ERROR O VARIACIÓN | E33: 0.06 | F33: =+F32*E33 -> 151.253
A34: COSTO DE UNA PORCION + EL MARGEN DE ERROR | F34: =+F32+F33 -> 2672.1363
A35: COSTO TOTAL DE UNA PORCION | F35: =+F32/F24 -> 2520.8833
A36: COSTO TOTAL DE LOS INGREDIENTES | F36: =+F34 -> 2672.1363
A39: WAFFLES
A40: RECETAS ESTANDAR ALMA RURAL 2025
E41: RECETA #
E42: # PORCIONES | F42: 2
A43: COD. | B43: INGREDIENTES | C43: UNID | D43: CANT. | E43: V/UNIT. | F43: V/TOTAL
B44: HARINA DE TRIGO | C44: GR | D44: 60 | E44: =+'LISTA MAESTRA'!D96 -> 3.4 | F44: =+E44*D44 -> 204
B45: HARINA DE YUCA | C45: GR | D45: 30 | E45: =+'LISTA MAESTRA'!D97 -> 39 | F45: =+E45*D45 -> 1170
B46: HUEVO | C46: UNIDAD | D46: 1 | E46: =+'LISTA MAESTRA'!D39 -> 433.33333 | F46: =+E46*D46 -> 433.33333
B47: LECHE | C47: CC | D47: 120 | E47: =+'LISTA MAESTRA'!D72 -> 3.65 | F47: =+E47*D47 -> 438
B48: QUESO CRIOLLO | C48: GR | D48: 0 | E48: =+'LISTA MAESTRA'!D74 -> 23.4 | F48: =+E48*D48 -> 0
B49: AZUCAR | C49: GR | D49: 20 | E49: =+'LISTA MAESTRA'!D92 -> 4.5 | F49: =+E49*D49 -> 90
B50: SAL | C50: GR | D50: 1 | E50: =+'LISTA MAESTRA'!D95 -> 2.4666667 | F50: =+E50*D50 -> 2.4666667
B51: POLVO DE HORNEAR | C51: GR | D51: 1 | E51: =+'LISTA MAESTRA'!D98 -> 95 | F51: =+E51*D51 -> 95
B52: ESENCIA | C52: GOTA | D52: 1 | E52: =+'LISTA MAESTRA'!D117 -> 13.4 | F52: =+E52*D52 -> 13.4
B53: CHIPS DE CHOCOLATE | C53: GR | D53: 10 | E53: =+'LISTA MAESTRA'!D88 -> 42.408 | F53: =+E53*D53 -> 424.08
A56: COSTO TOTAL DE LOS INGREDIENTES | F56: =SUM(F44:F55) -> 2870.28
A57: MARGEN DE ERROR O VARIACIÓN | E57: 0.03 | F57: =+F56*E57 -> 86.1084
A58: COSTO DE UNA PORCION + EL MARGEN DE ERROR | F58: =+F56+F57 -> 2956.3884
A59: COSTO TOTAL DE UNA PORCION | F59: =+F56/F42 -> 1435.14
A60: COSTO TOTAL DE LOS INGREDIENTES | F60: =+F58 -> 2956.3884
A63: CHOCOLATE CALIENTE
A64: RECETAS ESTANDAR ALMA RURAL 2025
E65: RECETA #
E66: # PORCIONES | F66: 1
A67: COD. | B67: INGREDIENTES | C67: UNID | D67: CANT. | E67: V/UNIT. | F67: V/TOTAL
B68: PASTILLA DE CHOCOLATE | C68: UND | D68: 1 | E68: =+'LISTA MAESTRA'!D101 -> 493.75 | F68: =E68*D68 -> 493.75
B69: LECHE | C69: CC | D69: 300 | E69: =+'LISTA MAESTRA'!D72 -> 3.65 | F69: =E69*D69 -> 1095
F70: =E70*D70 -> 0
A71: COSTO TOTAL DE LOS INGREDIENTES | F71: =SUM(F68:F70) -> 1588.75
A72: MARGEN DE ERROR O VARIACIÓN | E72: 0.06 | F72: =+F71*E72 -> 95.325
A73: COSTO DE UNA PORCION + EL MARGEN DE ERROR | F73: =+F71+F72 -> 1684.075
A74: COSTO TOTAL DE UNA PORCION | F74: =+F71/F66 -> 1588.75
A75: COSTO TOTAL DE LOS INGREDIENTES | F75: =+F73 -> 1684.075
A78: BATIDO VERDE
A79: RECETAS ESTANDAR ALMA RURAL 2025
A80: RESTAURANTE ALMA | E80: RECETA #
E81: # PORCIONES | F81: 1
A82: COD. | B82: INGREDIENTES | C82: UNID | D82: CANT. | E82: V/UNIT. | F82: V/TOTAL
B83: ESPINCA | C83: GR | D83: 50 | E83: =+'LISTA MAESTRA'!D41 -> 17 | F83: =E83*D83 -> 850
B84: MANZA VERDE | C84: UNIDAD | D84: 0.5 | E84: =+'LISTA MAESTRA'!D50 -> 2600 | F84: =E84*D84 -> 1300
B85: PEPINO COHOMBRO | C85: GRAMOS | D85: 200 | E85: =+'LISTA MAESTRA'!D51 -> 3.7 | F85: =E85*D85 -> 740
B86: PIÑA | C86: GRAMOS | D86: 100 | E86: =+'LISTA MAESTRA'!D52 -> 3.5 | F86: =E86*D86 -> 350
B87: LIMON | C87: CC | D87: 300 | E87: =+'LISTA MAESTRA'!D47 -> 5.7 | F87: =E87*D87 -> 1710
F88: =E88*D88 -> 0
F89: =E89*D89 -> 0
A90: COSTO TOTAL DE LOS INGREDIENTES | F90: =SUM(F83:F89) -> 4950
A91: MARGEN DE ERROR O VARIACIÓN | E91: 0.06 | F91: =+F90*E91 -> 297
A92: COSTO DE UNA PORCION + EL MARGEN DE ERROR | F92: =+F90+F91 -> 5247
A93: COSTO TOTAL DE UNA PORCION | F93: =+F90/F81 -> 4950
A94: COSTO TOTAL DE LOS INGREDIENTES | F94: =+F92 -> 5247
A97: PORCION DE PATACONAS
A98: RECETAS ESTANDAR ALMA RURAL 2025
A99: NOMBRE DEL ESTUDIANTE: | E99: RECETA #
E100: # PORCIONES | F100: 1
A101: COD. | B101: INGREDIENTES | C101: UNID | D101: CANT. | E101: V/UNIT. | F101: V/TOTAL
B102: PLATANO VERDE | C102: GR | D102: 500 | E102: =+'LISTA MAESTRA'!D59 -> 7 | F102: =E102*D102 -> 3500
B103: ACEITE | C103: CC | D103: 120 | E103: =+'LISTA MAESTRA'!D102 -> 9.92 | F103: =E103*D103 -> 1190.4
F104: =E104*D104 -> 0
A105: COSTO TOTAL DE LOS INGREDIENTES | F105: =SUM(F102:F104) -> 4690.4
A106: MARGEN DE ERROR O VARIACIÓN | E106: 0.06 | F106: =+F105*E106 -> 281.424
A107: COSTO DE UNA PORCION + EL MARGEN DE ERROR | F107: =+F105+F106 -> 4971.824
A108: COSTO TOTAL DE UNA PORCION | F108: =+F105/F100 -> 4690.4
A109: COSTO TOTAL DE LOS INGREDIENTES | F109: =+F107 -> 4971.824
A111: ABORRAJADOS
A112: RECETAS ESTANDAR ALMA RURAL 2025
A113: RESTAURANTE ALMA | E113: RECETA #
E114: # PORCIONES | F114: 10
...

Sheet ESTANDAR CAMPO
A1: CAMPESINO
A2: RECETAS ESTANDAR ALMA RURAL 2025 | H2: LISTA MAESTRA | I2: 'RECETA BASE'
A3: : | E3: # RECETA | F3: 1
E4: # PORCIONES | F4: 1
A5: COD. | B5: INGREDIENTES | C5: UNID | D5: CANT. | E5: V/UNIT. | F5: V/TOTAL
B6: CALDO DE ALAS | C6: PORCION | D6: 1 | E6: =+'RECETA BASE'!F16 -> 2348.96 | F6: =+E6*D6 -> 2348.96
B7: HUEVOS CRIOLLOS | C7: PORCION | D7: 1 | E7: =+'RECETA BASE'!F34 -> 2672.1363 | F7: =+E7*D7 -> 2672.1363
B8: AREPA | C8: UND | D8: 1 | E8: =+'LISTA MAESTRA'!D38 -> 100 | F8: =+E8*D8 -> 100
B9: QUESO CRIOLLO | C9: GR | D9: 50 | E9: =+'LISTA MAESTRA'!D74 -> 23.4 | F9: =+E9*D9 -> 1170
B10: WAFFLE MEDIA PORCION | C10: PORC | D10: 1 | E10: =+'RECETA BASE'!F59 -> 1435.14 | F10: =+E10*D10 -> 1435.14
B11: BEBIDA DE ELECCIÓN | C11: PORC | D11: 1 | E11: =+'RECETA BASE'!F73 -> 1684.075 | F11: =+E11*D11 -> 1684.075
B12: BIZCOCHOS | C12: UND | D12: 5 | E12: =+'LISTA MAESTRA'!D111 -> 216.4 | F12: =+E12*D12 -> 1082
A14: COSTO TOTAL DE LOS INGREDIENTES | F14: =SUM(F6:F13) -> 10492.311
A15: MARGEN DE ERROR O VARIACIÓN | E15: 0 | F15: =+F14*E15 -> 0
A16: COSTO TOTAL DE LA PREPARACIÓN + MARGEN DE ERROR | F16: =+F14+F15 -> 10492.311
A17: COSTO DE UNA PORCIÓN SUMANDO EL MARGEN DE ERROR | F17: =+F16/F4 -> 10492.311
A18: % COSTO MATERIA PRIMA ESTABLECIDO POR GERENCIA | F18: 0.35
A19: PRECIO POTENCIAL DE VENTA DE UNA PORCIÓN | F19: =+F17/F18 -> 29978.032
A20: PRECIO REAL DE VENTA DE UNA PORCIÓN | F20: =ROUNDUP(F19,-2) -> 30000
A21: % REAL DE COSTO (COSTO PORCIÓN SOBRE PRECIO REAL VENTA) | F21: =+F17/F20 -> 0.34974371
A22: IVA GENERADO AL VENDER CADA PORCIÓN | E22: 0.08 | F22: =+F20*E22 -> 2400
A23: PRECIO PARA LA CARTA DE CADA PORCIÓN | F23: =+F20+F22 -> 32400
A26: HUEVOS EN CACEROLA
A27: RECETAS ESTANDAR ALMA RURAL 2025
A28: : | E28: # RECETA | F28: 2
E29: # PORCIONES | F29: 1
A30: COD. | B30: INGREDIENTES | C30: UNID | D30: CANT. | E30: V/UNIT. | F30: V/TOTAL
B31: HUEVO | C31: UND | D31: 2 | E31: =+'LISTA MAESTRA'!D39 -> 433.33333 | F31: =E31*D31 -> 866.66667
B32: MARGARINA | C32: GR | D32: 25 | E32: =+'LISTA MAESTRA'!D87 -> 17.2625 | F32: =E32*D32 -> 431.5625
B33: VEGETALES DE LA HUERTA | F33: =E33*D33 -> 0
B34: BEBIDA DE ELECCIÓN | C34: PORC | D34: 1 | E34: =+'RECETA BASE'!F73 -> 1684.075 | F34: =E34*D34 -> 1684.075
B35: AREPA | C35: UND | D35: 1 | E35: =+'LISTA MAESTRA'!D38 -> 100 | F35: =E35*D35 -> 100
B36: BIZCOCHOS DE ACHIRA | C36: UND | D36: 5 | E36: =+'LISTA MAESTRA'!D111 -> 216.4 | F36: =E36*D36 -> 1082
B37: WAFLE MEDIA PORCION | C37: PORC | D37: 1 | E37: =+'RECETA BASE'!F59 -> 1435.14 | F37: =E37*D37 -> 1435.14
F38: =E38*D38 -> 0
F39: =E39*D39 -> 0
A40: COSTO TOTAL DE LOS INGREDIENTES | F40: =SUM(F31:F39) -> 5599.4442
A41: MARGEN DE ERROR O VARIACIÓN | E41: 0 | F41: =+F40*E41 -> 0
A42: COSTO TOTAL DE LA PREPARACIÓN + MARGEN DE ERROR | F42: =+F40+F41 -> 5599.4442
A43: COSTO DE UNA PORCIÓN SUMANDO EL MARGEN DE ERROR | F43: =+F42/F29 -> 5599.4442
A44: % COSTO MATERIA PRIMA ESTABLECIDO POR GERENCIA | F44: 0.35
A45: PRECIO POTENCIAL DE VENTA DE UNA PORCIÓN | F45: =+F43/F44 -> 15998.412
A46: PRECIO REAL DE VENTA DE UNA PORCIÓN | F46: =ROUNDUP(F45,-2) -> 16000
A47: % REAL DE COSTO (COSTO PORCIÓN SOBRE PRECIO REAL VENTA) | F47: =+F43/F46 -> 0.34996526
A48: IVA GENERADO AL VENDER CADA PORCIÓN | E48: 0.08 | F48: =+F46*E48 -> 1280
A49: PRECIO PARA LA CARTA DE CADA PORCIÓN | F49: =+F46+F48 -> 17280
A52: HUEVOS NAPOLITANOS
A53: RECETAS ESTANDAR ALMA RURAL 2025
A54: : | E54: # RECETA | F54: 3
E55: # PORCIONES | F55: 1
A56: COD. | B56: INGREDIENTES | C56: UNID | D56: CANT. | E56: V/UNIT. | F56: V/TOTAL
B57: HUEVOS | C57: UND | D57: 2 | E57: =+'LISTA MAESTRA'!D39 -> 433.33333 | F57: =+E57*D57 -> 866.66667
B58: SALSA NAPOLITANA | C58: PORC | D58: 1 | E58: 1600 | F58: =+E58*D58 -> 1600
B59: ALBAHACA | C59: GR | D59: 4 | E59: =+'LISTA MAESTRA'!D120 -> 26 | F59: =+E59*D59 -> 104
B60: BEBIDA DE ELECCIÓN | C60: PORC | D60: 1 | E60: =+'RECETA BASE'!F73 -> 1684.075 | F60: =+E60*D60 -> 1684.075
B61: AREPA | C61: UND | D61: 1 | E61: =+'LISTA MAESTRA'!D38 -> 100 | F61: =+E61*D61 -> 100
B62: BISCOCHO | C62: UND | D62: 5 | E62: =+'LISTA MAESTRA'!D111 -> 216.4 | F62: =+E62*D62 -> 1082
B63: WAFLE | C63: PORC | D63: 1 | E63: =+'RECETA BASE'!F59 -> 1435.14 | F63: =+E63*D63 -> 1435.14
B64: QUESO CRIOLLO | C64: GR | D64: 150 | E64: =+'LISTA MAESTRA'!D74 -> 23.4 | F64: =+E64*D64 -> 3510
A66: COSTO TOTAL DE LOS INGREDIENTES | F66: =SUM(F57:F65) -> 10381.882
A67: MARGEN DE ERROR O VARIACIÓN | E67: 0 | F67: =+F66*E67 -> 0
A68: COSTO TOTAL DE LA PREPARACIÓN + MARGEN DE ERROR | F68: =+F66+F67 -> 10381.882
A69: COSTO DE UNA PORCIÓN SUMANDO EL MARGEN DE ERROR | F69: =+F68/F55 -> 10381.882
A70: % COSTO MATERIA PRIMA ESTABLECIDO POR GERENCIA | F70: 0.3
A71: PRECIO POTENCIAL DE VENTA DE UNA PORCIÓN | F71: =+F69/F70 -> 34606.272
A72: PRECIO REAL DE VENTA DE UNA PORCIÓN | F72: =ROUNDUP(F71,-2) -> 34700
A73: % REAL DE COSTO (COSTO PORCIÓN SOBRE PRECIO REAL VENTA) | F73: =+F69/F72 -> 0.29918967
A74: IVA GENERADO AL VENDER CADA PORCIÓN | E74: 0.08 | F74: =+F72*E74 -> 2776
A75: PRECIO PARA LA CARTA DE CADA PORCIÓN | F75: =+F72+F74 -> 37476
A78: OMELETTE
A79: TALLER DE COSTOS NOMADA CONSULTORIAS
A80: : | E80: # RECETA | F80: 4 Y 5
E81: # PORCIONES | F81: 1
A82: COD. | B82: INGREDIENTES | C82: UNID | D82: CANT. | E82: V/UNIT. | F82: V/TOTAL
B83: HUEVOS | C83: UND | D83: 2 | E83: =+'LISTA MAESTRA'!D39 -> 433.33333 | F83: =E83*D83 -> 866.66667
B84: TOPPIN | F84: =E84*D84 -> 0
B85: BEBIDA DE ELECCIÓN | C85: PORC | D85: 1 | E85: =+'RECETA BASE'!F73 -> 1684.075 | F85: =E85*D85 -> 1684.075
B86: AREPA | C86: UND | D86: 1 | E86: =+'LISTA MAESTRA'!D38 -> 100 | F86: =E86*D86 -> 100
B87: BISZCOCHOS DE ACHIRA | C87: UND | D87: 5 | E87: =+'LISTA MAESTRA'!D111 -> 216.4 | F87: =E87*D87 -> 1082
B88: WAFLE | C88: PORC | D88: 0.5 | E88: =+'RECETA BASE'!F59 -> 1435.14 | F88: =E88*D88 -> 717.57
B89: QUESO CRIOLLO | C89: GR | D89: 70 | E89: =+'LISTA MAESTRA'!D74 -> 23.4 | F89: =E89*D89 -> 1638
B90: MARGARINA | C90: GR | D90: 30 | E90: =+'LISTA MAESTRA'!D87 -> 17.2625 | F90: =E90*D90 -> 517.875
F91: =E91*D91 -> 0
A92: COSTO TOTAL DE LOS INGREDIENTES | F92: =SUM(F83:F91) -> 6606.1867
A93: MARGEN DE ERROR O VARIACIÓN | E93: 0 | F93: =+F92*E93 -> 0
A94: COSTO TOTAL DE LA PREPARACIÓN + MARGEN DE ERROR | F94: =+F92+F93 -> 6606.1867
A95: COSTO DE UNA PORCIÓN SUMANDO EL MARGEN DE ERROR | F95: =+F94/F81 -> 6606.1867
A96: % COSTO MATERIA PRIMA ESTABLECIDO POR GERENCIA | F96: 0.35
A97: PRECIO POTENCIAL DE VENTA DE UNA PORCIÓN | F97: =+F95/F96 -> 18874.819
A98: PRECIO REAL DE VENTA DE UNA PORCIÓN | F98: =ROUNDUP(F97,-2) -> 18900
A99: % REAL DE COSTO (COSTO PORCIÓN SOBRE PRECIO REAL VENTA) | F99: =+F95/F98 -> 0.34953369
A100: IVA GENERADO AL VENDER CADA PORCIÓN | E100: 0.08 | F100: =+F98*E100 -> 1512
A101: PRECIO PARA LA CARTA DE CADA PORCIÓN | F101: =+F98+F100 -> 20412

Sheet ESTANDAR SALUDABLE
A1: BOWL NUTRITIVO
A2: RECETAS ESTANDAR ALMA RURAL 2025 | H2: LISTA MAESTRA | I2: 'RECETA BASE'
A3: : | E3: # RECETA | F3: 6
E4: # PORCIONES | F4: 1
A5: COD. | B5: INGREDIENTES | C5: UNID | D5: CANT. | E5: V/UNIT. | F5: V/TOTAL
B6: YOGURT TARRITO | C6: UND | D6: 1 | E6: =+'LISTA MAESTRA'!D76 -> 2500 | F6: =+E6*D6 -> 2500
B7: FRUTAS | C7: PORC | D7: 1 | E7: =+'RECETA BASE'!F216 -> 4388.4 | F7: =+E7*D7 -> 4388.4
B8: GRANOLA | C8: GR | D8: 100 | E8: =+'LISTA MAESTRA'!D112 -> 15.4 | F8: =+E8*D8 -> 1540
F9: =+E9*D9 -> 0
A11: COSTO TOTAL DE LOS INGREDIENTES | F11: =SUM(F6:F10) -> 8428.4
A12: MARGEN DE ERROR O VARIACIÓN | E12: 0 | F12: =+F11*E12 -> 0
A13: COSTO TOTAL DE LA PREPARACIÓN + MARGEN DE ERROR | F13: =+F11+F12 -> 8428.4
A14: COSTO DE UNA PORCIÓN SUMANDO EL MARGEN DE ERROR | F14: =+F13/F4 -> 8428.4
A15: % COSTO MATERIA PRIMA ESTABLECIDO POR GERENCIA | F15: 0.35
A16: PRECIO POTENCIAL DE VENTA DE UNA PORCIÓN | F16: =+F14/F15 -> 24081.143
A17: PRECIO REAL DE VENTA DE UNA PORCIÓN | F17: =ROUNDUP(F16,-2) -> 24100
A18: % REAL DE COSTO (COSTO PORCIÓN SOBRE PRECIO REAL VENTA) | F18: =+F14/F17 -> 0.34972614
A19: IVA GENERADO AL VENDER CADA PORCIÓN | E19: 0.08 | F19: =+F17*E19 -> 1928
A20: PRECIO PARA LA CARTA DE CADA PORCIÓN | F20: =+F17+F19 -> 26028
A23: WAFFLES
A24: RECETAS ESTANDAR ALMA RURAL 2025
A25: : | E25: # RECETA | F25: 7
E26: # PORCIONES | F26: 1
A27: COD. | B27: INGREDIENTES | C27: UNID | D27: CANT. | E27: V/UNIT. | F27: V/TOTAL
B28: WAFLES COMPLETO | C28: UND | D28: 1 | E28: =+'RECETA BASE'!F56 -> 2870.28 | F28: =E28*D28 -> 2870.28
B29: YOGURT | C29: UND | D29: 1 | E29: =+'LISTA MAESTRA'!D76 -> 2500 | F29: =E29*D29 -> 2500
B30: BEBIDA CALIENTE | C30: PORCION | D30: 1 | E30: =+'RECETA BASE'!F73 -> 1684.075 | F30: =E30*D30 -> 1684.075
B31: FRUTAS | C31: PORCION | D31: 1 | E31: =+'RECETA BASE'!F216 -> 4388.4 | F31: =E31*D31 -> 4388.4
B32: QUESO CRIOLLO | C32: PORCION | D32: 50 | E32: =+'LISTA MAESTRA'!D74 -> 23.4 | F32: =E32*D32 -> 1170
B33: MERMELADA MORA O UCHUVA | C33: PORCION | D33: 1 | F33: =E33*D33 -> 0
A34: COSTO TOTAL DE LOS INGREDIENTES | F34: =SUM(F28:F33) -> 12612.755
A35: MARGEN DE ERROR O VARIACIÓN | E35: 0 | F35: =+F34*E35 -> 0
A36: COSTO TOTAL DE LA PREPARACIÓN + MARGEN DE ERROR | F36: =+F34+F35 -> 12612.755
A37: COSTO DE UNA PORCIÓN SUMANDO EL MARGEN DE ERROR | F37: =+F36/F26 -> 12612.755
A38: % COSTO MATERIA PRIMA ESTABLECIDO POR GERENCIA | F38: 0.35
A39: PRECIO POTENCIAL DE VENTA DE UNA PORCIÓN | F39: =+F37/F38 -> 36036.443
A40: PRECIO REAL DE VENTA DE UNA PORCIÓN | F40: =ROUNDUP(F39,-2) -> 36100
A41: % REAL DE COSTO (COSTO PORCIÓN SOBRE PRECIO REAL VENTA) | F41: =+F37/F40 -> 0.3493838
A42: IVA GENERADO AL VENDER CADA PORCIÓN | E42: 0.08 | F42: =+F40*E42 -> 2888
A43: PRECIO PARA LA CARTA DE CADA PORCIÓN | F43: =+F40+F42 -> 38988
A46: BATIDO VERDE
A47: RECETAS ESTANDAR ALMA RURAL 2025
A48: : | E48: # RECETA | F48: 8
E49: # PORCIONES | F49: 1
A50: COD. | B50: INGREDIENTES | C50: UNID | D50: CANT. | E50: V/UNIT. | F50: V/TOTAL
B51: BATIDO VERDE PORCION | C51: PORCI | D51: 1 | E51: =+'RECETA BASE'!F92 -> 5247 | F51: =+E51*D51 -> 5247
A53: COSTO TOTAL DE LOS INGREDIENTES | F53: =SUM(F51:F52) -> 5247
A54: MARGEN DE ERROR O VARIACIÓN | E54: 0 | F54: =+F53*E54 -> 0
A55: COSTO TOTAL DE LA PREPARACIÓN + MARGEN DE ERROR | F55: =+F53+F54 -> 5247
A56: COSTO DE UNA PORCIÓN SUMANDO EL MARGEN DE ERROR | F56: =+F55/F49 -> 5247
A57: % COSTO MATERIA PRIMA ESTABLECIDO POR GERENCIA | F57: 0.3
A58: PRECIO POTENCIAL DE VENTA DE UNA PORCIÓN | F58: =+F56/F57 -> 17490
A59: PRECIO REAL DE VENTA DE UNA PORCIÓN | F59: =ROUNDUP(F58,-2) -> 17500
A60: % REAL DE COSTO (COSTO PORCIÓN SOBRE PRECIO REAL VENTA) | F60: =+F56/F59 -> 0.29982857
A61: IVA GENERADO AL VENDER CADA PORCIÓN | E61: 0.08 | F61: =+F59*E61 -> 1400
A62: PRECIO PARA LA CARTA DE CADA PORCIÓN | F62: =+F59+F61 -> 18900

Sheet ESTANDAR ENTRADAS
A1: PATACONES DE LAS MONTAÑAS COLOMBIANAS
A2: RECETAS ESTANDAR ALMA RURAL 2025 | H2: LISTA MAESTRA | I2: 'RECETA BASE'
A3: : | E3: # RECETA | F3: 9
E4: # PORCIONES | F4: 1
A5: COD. | B5: INGREDIENTES | C5: UNID | D5: CANT. | E5: V/UNIT. | F5: V/TOTAL
B6: PLATANO VERDE | C6: PORC | D6: 1 | E6: =+'RECETA BASE'!F107 -> 4971.824 | F6: =+E6*D6 -> 4971.824
B7: SALSA CRIOLLA | C7: PORC | D7: 1 | E7: =+'RECETA BASE'!F252 -> 805.54906 | F7: =+E7*D7 -> 805.54906
B8: QUESO CRIOLLO | C8: GR | D8: 100 | E8: =+'LISTA MAESTRA'!D74 -> 23.4 | F8: =+E8*D8 -> 2340
A10: COSTO TOTAL DE LOS INGREDIENTES | F10: =SUM(F6:F9) -> 8117.3731
A11: MARGEN DE ERROR O VARIACIÓN | E11: 0 | F11: =+F10*E11 -> 0
A12: COSTO TOTAL DE LA PREPARACIÓN + MARGEN DE ERROR | F12: =+F10+F11 -> 8117.3731
A13: COSTO DE UNA PORCIÓN SUMANDO EL MARGEN DE ERROR | F13: =+F12/F4 -> 8117.3731
A14: % COSTO MATERIA PRIMA ESTABLECIDO POR GERENCIA | F14: 0.35
A15: PRECIO POTENCIAL DE VENTA DE UNA PORCIÓN | F15: =+F13/F14 -> 23192.494
A16: PRECIO REAL DE VENTA DE UNA PORCIÓN | F16: =ROUNDUP(F15,-2) -> 23200
A17: % REAL DE COSTO (COSTO PORCIÓN SOBRE PRECIO REAL VENTA) | F17: =+F13/F16 -> 0.34988677
A18: IVA GENERADO AL VENDER CADA PORCIÓN | E18: 0.08 | F18: =+F16*E18 -> 1856
A19: PRECIO PARA LA CARTA DE CADA PORCIÓN | F19: =+F16+F18 -> 25056
A22: DULCE TENTACION ABORRAJADA
A23: RECETAS ESTANDAR ALMA RURAL 2025
A24: : | E24: # RECETA | F24: 10
E25: # PORCIONES | F25: 1
A26: COD. | B26: INGREDIENTES | C26: UNID | D26: CANT. | E26: V/UNIT. | F26: V/TOTAL
B27: ABORRAJADO | C27: PORCI | D27: 3 | E27: =+'RECETA BASE'!F128 -> 1305.9667 | F27: =E27*D27 -> 3917.9
B28: BOCADILLO | C28: GR | D28: 20 | E28: =+'LISTA MAESTRA'!D113 -> 15.06 | F28: =E28*D28 -> 301.2
F30: 0
A31: COSTO TOTAL DE LOS INGREDIENTES | F31: =SUM(F27:F30) -> 4219.1
A32: MARGEN DE ERROR O VARIACIÓN | E32: 0 | F32: =+F31*E32 -> 0
A33: COSTO TOTAL DE LA PREPARACIÓN + MARGEN DE ERROR | F33: =+F31+F32 -> 4219.1
A34: COSTO DE UNA PORCIÓN SUMANDO EL MARGEN DE ERROR | F34: =+F33/F25 -> 4219.1
A35: % COSTO MATERIA PRIMA ESTABLECIDO POR GERENCIA | F35: 0.35
A36: PRECIO POTENCIAL DE VENTA DE UNA PORCIÓN | F36: =+F34/F35 -> 12054.571
A37: PRECIO REAL DE VENTA DE UNA PORCIÓN | F37: =ROUNDUP(F36,-2) -> 12100
A38: % REAL DE COSTO (COSTO PORCIÓN SOBRE PRECIO REAL VENTA) | F38: =+F34/F37 -> 0.34868595
A39: IVA GENERADO AL VENDER CADA PORCIÓN | E39: 0.08 | F39: =+F37*E39 -> 968
A40: PRECIO PARA LA CARTA DE CADA PORCIÓN | F40: =+F37+F39 -> 13068
A43: CHICHARRON CAMPESINO
A44: RECETAS ESTANDAR ALMA RURAL 2025
A45: : | E45: # RECETA | F45: 11
E46: # PORCIONES | F46: 1
A47: COD. | B47: INGREDIENTES | C47: UNID | D47: CANT. | E47: V/UNIT. | F47: V/TOTAL
B48: TOCINO CARNUDO | C48: GR | D48: 500 | E48: =+'LISTA MAESTRA'!D23 -> 28 | F48: =+E48*D48 -> 14000
B49: PORCION PAPAS CASCO | C49: PORCION | D49: 1 | E49: =+'RECETA BASE'!F142 -> 2184.024 | F49: =+E49*D49 -> 2184.024
B50: SALSAS DE LA CASA | C50: PORCION | D50: 1 | F50: =+E50*D50 -> 0
B51: AGUACATE | C51: GR | D51: 100 | E51: =+'LISTA MAESTRA'!D37 -> 12 | F51: =+E51*D51 -> 1200
B52: CEBOLLA MORADA | C52: GR | D52: 50 | E52: =+'LISTA MAESTRA'!D49 -> 4.6 | F52: =+E52*D52 -> 230
B53: PIMENTON | C53: GR | D53: 50 | E53: =+'LISTA MAESTRA'!D60 -> 10.6 | F53: =+E53*D53 -> 530
B54: CILANTRO | C54: GR | D54: 10 | E54: =+'LISTA MAESTRA'!D62 -> 3.4 | F54: =+E54*D54 -> 34
B55: LIMON | C55: GR | D55: 100 | E55: =+'LISTA MAESTRA'!D47 -> 5.7 | F55: =+E55*D55 -> 570
B56: MARINADA | C56: PORCION | D56: 1 | E56: =+'RECETA BASE'!F272 -> 1520.4375 | F56: =+E56*D56 -> 1520.4375
A58: COSTO TOTAL DE LOS INGREDIENTES | F58: =SUM(F48:F57) -> 20268.461
A59: MARGEN DE ERROR O VARIACIÓN | E59: 0 | F59: =+F58*E59 -> 0
A60: COSTO TOTAL DE LA PREPARACIÓN + MARGEN DE ERROR | F60: =+F58+F59 -> 20268.461
A61: COSTO DE UNA PORCIÓN SUMANDO EL MARGEN DE ERROR | F61: =+F60/F46 -> 20268.461
A62: % COSTO MATERIA PRIMA ESTABLECIDO POR GERENCIA | F62: 0.3
A63: PRECIO POTENCIAL DE VENTA DE UNA PORCIÓN | F63: =+F61/F62 -> 67561.538
A64: PRECIO REAL DE VENTA DE UNA PORCIÓN | F64: =ROUNDUP(F63,-2) -> 67600
A65: % REAL DE COSTO (COSTO PORCIÓN SOBRE PRECIO REAL VENTA) | F65: =+F61/F64 -> 0.29982931
A66: IVA GENERADO AL VENDER CADA PORCIÓN | E66: 0.08 | F66: =+F64*E66 -> 5408
A67: PRECIO PARA LA CARTA DE CADA PORCIÓN | F67: =+F64+F66 -> 73008

Sheet AVES DEL CORRAL
A1: BROCHETAS DE POLLO A LA BRASA
A2: RECETAS ESTANDAR ALMA RURAL 2025 | H2: LISTA MAESTRA | I2: 'RECETA BASE'
A3: : | E3: # RECETA | F3: 12
E4: # PORCIONES | F4: 1
A5: COD. | B5: INGREDIENTES | C5: UNID | D5: CANT. | E5: V/UNIT. | F5: V/TOTAL
B6: BROCHETA PORCION | C6: PORCION | D6: 2 | E6: =+'RECETA BASE'!F165 -> 5093.851 | F6: =+E6*D6 -> 10187.702
B7: PORCION ENSALADA | C7: PORCION | D7: 1 | E7: =+'RECETA BASE'!F331 -> 1020.515 | F7: =+E7*D7 -> 1020.515
B8: PAPAS EN CASCO | C8: PORCION | D8: 1 | E8: =+'RECETA BASE'!F142 -> 2184.024 | F8: =+E8*D8 -> 2184.024
B9: ALIOLI | C9: PORCION | D9: 1 | F9: =+E9*D9 -> 0
B10: SALSA DE UCHUVA | C10: PORCION | F10: =+E10*D10 -> 0
A12: COSTO TOTAL DE LOS INGREDIENTES | F12: =SUM(F6:F11) -> 13392.241
A13: MARGEN DE ERROR O VARIACIÓN | E13: 0 | F13: =+F12*E13 -> 0
A14: COSTO TOTAL DE LA PREPARACIÓN + MARGEN DE ERROR | F14: =+F12+F13 -> 13392.241
A15: COSTO DE UNA PORCIÓN SUMANDO EL MARGEN DE ERROR | F15: =+F14/F4 -> 13392.241
A16: % COSTO MATERIA PRIMA ESTABLECIDO POR GERENCIA | F16: 0.35
A17: PRECIO POTENCIAL DE VENTA DE UNA PORCIÓN | F17: =+F15/F16 -> 38263.546
A18: PRECIO REAL DE VENTA DE UNA PORCIÓN | F18: =ROUNDUP(F17,-2) -> 38300
A19: % REAL DE COSTO (COSTO PORCIÓN SOBRE PRECIO REAL VENTA) | F19: =+F15/F18 -> 0.34966687
A20: IVA GENERADO AL VENDER CADA PORCIÓN | E20: 0.08 | F20: =+F18*E20 -> 3064
A21: PRECIO PARA LA CARTA DE CADA PORCIÓN | F21: =+F18+F20 -> 41364
A24: POLLO CRIOLLO SALTEADO (NO SE PIDE LA PECHUGA PORCIONADA DICEN QUE LA MERMA ES MAS DE LA MITAD
A25: RECETAS ESTANDAR ALMA RURAL 2025
A26: : | E26: # RECETA | F26: 13
E27: # PORCIONES | F27: 1
A28: COD. | B28: INGREDIENTES | C28: UNID | D28: CANT. | E28: V/UNIT. | F28: V/TOTAL
B29: PECHUGA DE POLLO * 350 GR | C29: GR | D29: 400 | E29: =+'LISTA MAESTRA'!D30 -> 23.4 | F29: =E29*D29 -> 9360
B30: ARROZ PORCION | C30: PORC | D30: 1 | E30: =+'RECETA BASE'!F184 -> 685.47083 | F30: =E30*D30 -> 685.47083 | J30: 24000 | K30: =+J30/2000 -> 12 | M30: =+K30*150 -> 1800
B31: PAPAS EN CASCO | C31: PORC | D31: 1 | E31: =+'RECETA BASE'!F142 -> 2184.024 | F31: =E31*D31 -> 2184.024
B32: VINO BLANCO COCINA | C32: CC | D32: 40 | E32: =+'LISTA MAESTRA'!D115 -> 30.666667 | F32: =E32*D32 -> 1226.6667
B33: SALSA CRIOLLA | C33: PORCION | D33: 1 | E33: =+'RECETA BASE'!F252 -> 805.54906 | F33: =E33*D33 -> 805.54906 | L33: =2000/150 -> 13.333333
B34: AJONJOLI | C34: GR | D34: 10 | E34: =+'LISTA MAESTRA'!D121 -> 17.5 | F34: =E34*D34 -> 175
F35: =E35*D35 -> 0
A37: COSTO TOTAL DE LOS INGREDIENTES | F37: =SUM(F29:F36) -> 14436.711
A38: MARGEN DE ERROR O VARIACIÓN | E38: 0 | F38: =+F37*E38 -> 0
A39: COSTO TOTAL DE LA PREPARACIÓN + MARGEN DE ERROR | F39: =+F37+F38 -> 14436.711
A40: COSTO DE UNA PORCIÓN SUMANDO EL MARGEN DE ERROR | F40: =+F39/F27 -> 14436.711
A41: % COSTO MATERIA PRIMA ESTABLECIDO POR GERENCIA | F41: 0.35
A42: PRECIO POTENCIAL DE VENTA DE UNA PORCIÓN | F42: =+F40/F41 -> 41247.744
A43: PRECIO REAL DE VENTA DE UNA PORCIÓN | F43: =ROUNDUP(F42,-2) -> 41300
A44: % REAL DE COSTO (COSTO PORCIÓN SOBRE PRECIO REAL VENTA) | F44: =+F40/F43 -> 0.34955716
A45: IVA GENERADO AL VENDER CADA PORCIÓN | E45: 0.08 | F45: =+F43*E45 -> 3304
A46: PRECIO PARA LA CARTA DE CADA PORCIÓN | F46: =+F43+F45 -> 44604
A49: PECHUGA DE POLLO A LA PARRILLA
A50: RECETAS ESTANDAR ALMA RURAL 2025
A51: : | E51: # RECETA | F51: 14
E52: # PORCIONES | F52: 1
A53: COD. | B53: INGREDIENTES | C53: UNID | D53: CANT. | E53: V/UNIT. | F53: V/TOTAL
B54: PECHUGA DE POLLO * 350 GR | C54: GR | D54: 400 | E54: =+'LISTA MAESTRA'!D30 -> 23.4 | F54: =+E54*D54 -> 9360
B55: PORCION DE ENSALADA | C55: PORCION | D55: 1 | E55: =+'RECETA BASE'!F331 -> 1020.515 | F55: =+E55*D55 -> 1020.515
B56: PAPAS EN CASCO | C56: PORCION | D56: 1 | E56: =+'RECETA BASE'!F142 -> 2184.024 | F56: =+E56*D56 -> 2184.024
B57: ADOBO | C57: PORCION | D57: 1 | E57: =+'RECETA BASE'!F314 -> 558.18413 | F57: =+E57*D57 -> 558.18413
B58: SAL PARRILLERA | C58: GR | D58: 1 | E58: =+'LISTA MAESTRA'!D105 -> 28.157895 | F58: =+E58*D58 -> 28.157895
F59: =+E59*D59 -> 0
A60: COSTO TOTAL DE LOS INGREDIENTES | F60: =SUM(F54:F59) -> 13150.881
A61: MARGEN DE ERROR O VARIACIÓN | E61: 0 | F61: =+F60*E61 -> 0
A62: COSTO TOTAL DE LA PREPARACIÓN + MARGEN DE ERROR | F62: =+F60+F61 -> 13150.881
A63: COSTO DE UNA PORCIÓN SUMANDO EL MARGEN DE ERROR | F63: =+F62/F52 -> 13150.881
A64: % COSTO MATERIA PRIMA ESTABLECIDO POR GERENCIA | F64: 0.3
A65: PRECIO POTENCIAL DE VENTA DE UNA PORCIÓN | F65: =+F63/F64 -> 43836.27
A66: PRECIO REAL DE VENTA DE UNA PORCIÓN | F66: =ROUNDUP(F65,-2) -> 43900
A67: % REAL DE COSTO (COSTO PORCIÓN SOBRE PRECIO REAL VENTA) | F67: =+F63/F66 -> 0.29956449
A68: IVA GENERADO AL VENDER CADA PORCIÓN | E68: 0.08 | F68: =+F66*E68 -> 3512
A69: PRECIO PARA LA CARTA DE CADA PORCIÓN | F69: =+F66+F68 -> 47412
A71: PECHUGA DE POLLO EN SALSA DE CHAMPIÑONES
A72: RECETAS ESTANDAR ALMA RURAL 2025
A73: : | E73: # RECETA | F73: 15
E74: # PORCIONES | F74: 1
A75: COD. | B75: INGREDIENTES | C75: UNID | D75: CANT. | E75: V/UNIT. | F75: V/TOTAL
B76: PECHUGA DE POLLO * 350 GR | C76: GR | D76: 400 | E76: =+'LISTA MAESTRA'!D30 -> 23.4 | F76: =+E76*D76 -> 9360
B77: PORCION ENSALADA | C77: PORCION | D77: 1 | E77: =+'RECETA BASE'!F331 -> 1020.515 | F77: =+E77*D77 -> 1020.515
B78: PAPAS EN CASCO | C78: PORCION | D78: 1 | E78: =+'RECETA BASE'!F142 -> 2184.024 | F78: =+E78*D78 -> 2184.024
B79: SALSA DE CHAMPIÑONES TRS CHAMPI | C79: PORCION | D79: 1 | E79: =+'RECETA BASE'!F202 -> 3239.793 | F79: =+E79*D79 -> 3239.793
B80: SAL | C80: GR | D80: 3 | E80: =+'LISTA MAESTRA'!D95 -> 2.4666667 | F80: =+E80*D80 -> 7.4
B81: PIMIENTA | C81: GR | D81: 1 | E81: =+'LISTA MAESTRA'!D107 -> 320 | F81: =+E81*D81 -> 320
B82: MARGARINA | C82: GR | D82: 30 | E82: =+'LISTA MAESTRA'!D87 -> 17.2625 | F82: =+E82*D82 -> 517.875
A84: COSTO TOTAL DE LOS INGREDIENTES | F84: =SUM(F76:F83) -> 16649.607
A85: MARGEN DE ERROR O VARIACIÓN | E85: 0 | F85: =+F84*E85 -> 0
A86: COSTO TOTAL DE LA PREPARACIÓN + MARGEN DE ERROR | F86: =+F84+F85 -> 16649.607
A87: COSTO DE UNA PORCIÓN SUMANDO EL MARGEN DE ERROR | F87: =+F86/F74 -> 16649.607
A88: % COSTO MATERIA PRIMA ESTABLECIDO POR GERENCIA | F88: 0.35
A89: PRECIO POTENCIAL DE VENTA DE UNA PORCIÓN | F89: =+F87/F88 -> 47570.306
A90: PRECIO REAL DE VENTA DE UNA PORCIÓN | F90: =ROUNDUP(F89,-2) -> 47600
A91: % REAL DE COSTO (COSTO PORCIÓN SOBRE PRECIO REAL VENTA) | F91: =+F87/F90 -> 0.34978166
A92: IVA GENERADO AL VENDER CADA PORCIÓN | E92: 0.08 | F92: =+F90*E92 -> 3808
A93: PRECIO PARA LA CARTA DE CADA PORCIÓN | F93: =+F90+F92 -> 51408

Sheet SABORES DE CERDO
A1: COSTILLAS EN SALSA BBQ
A2: RECETAS ESTANDAR ALMA RURAL 2025 | H2: LISTA MAESTRA | I2: 'RECETA BASE'
A3: : | E3: # RECETA | F3: 16
E4: # PORCIONES | F4: 1
A5: COD. | B5: INGREDIENTES | C5: UNID | D5: CANT. | E5: V/UNIT. | F5: V/TOTAL
B6: COSTILLAS DE CERDO * 500 GR | C6: GR | D6: 500 | E6: =+'LISTA MAESTRA'!D21 -> 23.6 | F6: =+E6*D6 -> 11800
B7: SALSA DE UCHUVA | C7: PORC | F7: =+E7*D7 -> 0
B8: PORCION DE ENSALADA | C8: PORCI | D8: 1 | E8: =+'RECETA BASE'!F331 -> 1020.515 | F8: =+E8*D8 -> 1020.515
B9: PAPAS EN CASCO | C9: PORCI | D9: 1 | E9: =+'RECETA BASE'!F142 -> 2184.024 | F9: =+E9*D9 -> 2184.024
B10: CARBON AL GASTO | F10: =+E10*D10 -> 0
B11: BOLSA PLASTICA | C11: UND | F11: =+E11*D11 -> 0
B12: SALSA DE ALIOLI | C12: PORCION | D12: 1 | F12: =+E12*D12 -> 0
A15: COSTO TOTAL DE LOS INGREDIENTES | F15: =SUM(F6:F14) -> 15004.539
A16: MARGEN DE ERROR O VARIACIÓN | E16: 0 | F16: =+F15*E16 -> 0
A17: COSTO TOTAL DE LA PREPARACIÓN + MARGEN DE ERROR | F17: =+F15+F16 -> 15004.539
A18: COSTO DE UNA PORCIÓN SUMANDO EL MARGEN DE ERROR | F18: =+F17/F4 -> 15004.539
A19: % COSTO MATERIA PRIMA ESTABLECIDO POR GERENCIA | F19: 0.35
A20: PRECIO POTENCIAL DE VENTA DE UNA PORCIÓN | F20: =+F18/F19 -> 42870.111
A21: PRECIO REAL DE VENTA DE UNA PORCIÓN | F21: =ROUNDUP(F20,-2) -> 42900
A22: % REAL DE COSTO (COSTO PORCIÓN SOBRE PRECIO REAL VENTA) | F22: =+F18/F21 -> 0.34975615
A23: IVA GENERADO AL VENDER CADA PORCIÓN | E23: 0.08 | F23: =+F21*E23 -> 3432
A24: PRECIO PARA LA CARTA DE CADA PORCIÓN | F24: =+F21+F23 -> 46332

Sheet TESOROS DEL RIO
A1: TRUCHA AHUMADA DE LA HUERTA
A2: RECETAS ESTANDAR ALMA RURAL 2025 | H2: LISTA MAESTRA | I2: 'RECETA BASE'
A3: : | E3: # RECETA | F3: 17
E4: # PORCIONES | F4: 1
A5: COD. | B5: INGREDIENTES | C5: UNID | D5: CANT. | E5: V/UNIT. | F5: V/TOTAL
B6: PORCION TRUCHA + 350 GR | C6: PORCION | D6: 1 | E6: =+'LISTA MAESTRA'!D14 -> 11484 | F6: =+E6*D6 -> 11484
B7: PORCION DE ENSALADA | C7: PORCION | D7: 1 | E7: =+'RECETA BASE'!F331 -> 1020.515 | F7: =+E7*D7 -> 1020.515
B8: PIMIENTA | C8: GR | D8: 2 | E8: =+'LISTA MAESTRA'!D107 -> 320 | F8: =+E8*D8 -> 640
B9: SAL | C9: GR | D9: 2 | E9: =+'LISTA MAESTRA'!D95 -> 2.4666667 | F9: =+E9*D9 -> 4.9333333
B10: ADOBO | C10: PORCIÓN | D10: 1 | E10: =+'RECETA BASE'!F314 -> 558.18413 | F10: =+E10*D10 -> 558.18413
B11: HOJA DE PLATANO | C11: UNIDAD | F11: =+E11*D11 -> 0
B12: CARBON AL GASTO | F12: =+E12*D12 -> 0
B13: PLATANO VERDE PORCION | C13: PORCION | D13: 0.5 | E13: =+'RECETA BASE'!F107 -> 4971.824 | F13: =+E13*D13 -> 2485.912
B14: PEREJIL | C14: GR | F14: =+E14*D14 -> 0
B15: TOMATE CHERRY | C15: GR | F15: =+E15*D15 -> 0
A18: COSTO TOTAL DE LOS INGREDIENTES | F18: =SUM(F6:F17) -> 16193.544
A19: MARGEN DE ERROR O VARIACIÓN | E19: 0 | F19: =+F18*E19 -> 0
A20: COSTO TOTAL DE LA PREPARACIÓN + MARGEN DE ERROR | F20: =+F18+F19 -> 16193.544
A21: COSTO DE UNA PORCIÓN SUMANDO EL MARGEN DE ERROR | F21: =+F20/F4 -> 16193.544
A22: % COSTO MATERIA PRIMA ESTABLECIDO POR GERENCIA | F22: 0.35
A23: PRECIO POTENCIAL DE VENTA DE UNA PORCIÓN | F23: =+F21/F22 -> 46267.27
A24: PRECIO REAL DE VENTA DE UNA PORCIÓN | F24: =ROUNDUP(F23,-2) -> 46300
A25: % REAL DE COSTO (COSTO PORCIÓN SOBRE PRECIO REAL VENTA) | F25: =+F21/F24 -> 0.34975258
A26: IVA GENERADO AL VENDER CADA PORCIÓN | E26: 0.08 | F26: =+F24*E26 -> 3704
A27: PRECIO PARA LA CARTA DE CADA PORCIÓN | F27: =+F24+F26 -> 50004
A30: TRUCHA A LA CRIOLLA
A31: RECETAS ESTANDAR ALMA RURAL 2025
A32: : | E32: # RECETA | F32: 18
E33: # PORCIONES | F33: 1
A34: COD. | B34: INGREDIENTES | C34: UNID | D34: CANT. | E34: V/UNIT. | F34: V/TOTAL
B35: PORCION DE TRUCHA * 350 | C35: PORCION | D35: 1 | E35: =+'LISTA MAESTRA'!D14 -> 11484 | F35: =E35*D35 -> 11484
B36: PORCION SALSA CRIOLLA | C36: PORCION | D36: 2 | E36: =+'RECETA BASE'!F252 -> 805.54906 | F36: =E36*D36 -> 1611.0981
B37: PAPAS EN CASCO | C37: PORCION | D37: 1 | E37: =+'RECETA BASE'!F143 -> 2060.4 | F37: =E37*D37 -> 2060.4
B38: MARGARINA | C38: GR | D38: 30 | E38: =+'LISTA MAESTRA'!D87 -> 17.2625 | F38: =E38*D38 -> 517.875
B39: PASTA DE AJO | C39: GR | D39: 1 | E39: =+'RECETA BASE'!F418 -> 502.5 | F39: =E39*D39 -> 502.5
B40: PIMIENTA | C40: GR | D40: 1 | E40: =+'LISTA MAESTRA'!D107 -> 320 | F40: =E40*D40 -> 320
B41: SAL | C41: GR | D41: 3 | E41: =+'LISTA MAESTRA'!D95 -> 2.4666667 | F41: =E41*D41 -> 7.4
B42: VINO BLANCO | C42: CC | D42: 30 | E42: =+'LISTA MAESTRA'!D115 -> 30.666667 | F42: =E42*D42 -> 920
F43: =E43*D43 -> 0
A44: COSTO TOTAL DE LOS INGREDIENTES | F44: =SUM(F35:F43) -> 17423.273
A45: MARGEN DE ERROR O VARIACIÓN | E45: 0 | F45: =+F44*E45 -> 0
A46: COSTO TOTAL DE LA PREPARACIÓN + MARGEN DE ERROR | F46: =+F44+F45 -> 17423.273
A47: COSTO DE UNA PORCIÓN SUMANDO EL MARGEN DE ERROR | F47: =+F46/F33 -> 17423.273
A48: % COSTO MATERIA PRIMA ESTABLECIDO POR GERENCIA | F48: 0.35
A49: PRECIO POTENCIAL DE VENTA DE UNA PORCIÓN | F49: =+F47/F48 -> 49780.78
A50: PRECIO REAL DE VENTA DE UNA PORCIÓN | F50: =ROUNDUP(F49,-2) -> 49800
A51: % REAL DE COSTO (COSTO PORCIÓN SOBRE PRECIO REAL VENTA) | F51: =+F47/F50 -> 0.34986492
A52: IVA GENERADO AL VENDER CADA PORCIÓN | E52: 0.08 | F52: =+F50*E52 -> 3984
A53: PRECIO PARA LA CARTA DE CADA PORCIÓN | F53: =+F50+F52 -> 53784
A56: TRUCHA CON CHAMPIÑONES
A57: RECETAS ESTANDAR ALMA RURAL 2025
A58: : | E58: # RECETA | F58: 19
E59: # PORCIONES | F59: 1
A60: COD. | B60: INGREDIENTES | C60: UNID | D60: CANT. | E60: V/UNIT. | F60: V/TOTAL
B61: TRUCHA PORCION * 350 GR | C61: PORCION | D61: 1 | E61: =+'LISTA MAESTRA'!D14 -> 11484 | F61: =+E61*D61 -> 11484
B62: PORCION SALSA DE CHAMPIÑONES | C62: PORCION | D62: 0.3 | E62: =+'RECETA BASE'!F202 -> 3239.793 | F62: =+E62*D62 -> 971.9379
B63: PAPAS EN CASCO | C63: PORCION | D63: 0.5 | E63: =+'RECETA BASE'!F143 -> 2060.4 | F63: =+E63*D63 -> 1030.2
B64: PORCION DE ARROZ | C64: PORCION | D64: 1 | E64: =+'RECETA BASE'!F184 -> 685.47083 | F64: =+E64*D64 -> 685.47083
B65: SAL | C65: GR | D65: 3 | E65: =+'LISTA MAESTRA'!D95 -> 2.4666667 | F65: =+E65*D65 -> 7.4
B66: PIMIENTA | C66: GR | D66: 1 | E66: =+'LISTA MAESTRA'!D107 -> 320 | F66: =+E66*D66 -> 320
B67: PASTA DE AJO | C67: GR | D67: 1 | E67: =+'RECETA BASE'!F418 -> 502.5 | F67: =+E67*D67 -> 502.5
B68: MARGARINA | C68: GR | D68: 15 | E68: =+'LISTA MAESTRA'!D87 -> 17.2625 | F68: =+E68*D68 -> 258.9375
A70: COSTO TOTAL DE LOS INGREDIENTES | F70: =SUM(F61:F69) -> 15260.446
A71: MARGEN DE ERROR O VARIACIÓN | E71: 0.03 | F71: =+F70*E71 -> 457.81339
A72: COSTO TOTAL DE LA PREPARACIÓN + MARGEN DE ERROR | F72: =+F70+F71 -> 15718.26
A73: COSTO DE UNA PORCIÓN SUMANDO EL MARGEN DE ERROR | F73: =+F72/F59 -> 15718.26
A74: % COSTO MATERIA PRIMA ESTABLECIDO POR GERENCIA | F74: 0.35
A75: PRECIO POTENCIAL DE VENTA DE UNA PORCIÓN | F75: =+F73/F74 -> 44909.313
A76: PRECIO REAL DE VENTA DE UNA PORCIÓN | F76: =ROUNDUP(F75,-2) -> 45000
A77: % REAL DE COSTO (COSTO PORCIÓN SOBRE PRECIO REAL VENTA) | F77: =+F73/F76 -> 0.34929466
A78: IVA GENERADO AL VENDER CADA PORCIÓN | E78: 0.08 | F78: =+F76*E78 -> 3600
A79: PRECIO PARA LA CARTA DE CADA PORCIÓN | F79: =+F76+F78 -> 48600
A81: TRUCHA AL AJILLO
A82: RECETAS ESTANDAR ALMA RURAL 2025
A83: : | E83: # RECETA | F83: 20
E84: # PORCIONES | F84: 1
A85: COD. | B85: INGREDIENTES | C85: UNID | D85: CANT. | E85: V/UNIT. | F85: V/TOTAL
B86: TRUCHA PORCION * 350 GR | C86: PORCION | D86: 1 | E86: =+'LISTA MAESTRA'!D14 -> 11484 | F86: =+E86*D86 -> 11484
B87: PORCION DE SALSA DE AJO | C87: PORCION | D87: 2 | E87: =+'RECETA BASE'!F420 -> 418.75 | F87: =+E87*D87 -> 837.5
B88: PAPAS EN CASCO | C88: PORCION | D88: 1 | E88: =+'RECETA BASE'!F143 -> 2060.4 | F88: =+E88*D88 -> 2060.4
B89: PORCION DE ARROZ | C89: PORCION | D89: 1 | E89: =+'RECETA BASE'!F184 -> 685.47083 | F89: =+E89*D89 -> 685.47083
B90: SAL | C90: GR | D90: 3 | E90: =+'LISTA MAESTRA'!D95 -> 2.4666667 | F90: =+E90*D90 -> 7.4
B91: PIMIENTA | C91: GR | D91: 1 | E91: =+'LISTA MAESTRA'!D107 -> 320 | F91: =+E91*D91 -> 320
B92: CEBOLLA CABEZONA PICADA | C92: GR | D92: 100 | E92: =+'LISTA MAESTRA'!D48 -> 3.7 | F92: =+E92*D92 -> 370
B93: VINO BLANCO | C93: CC | D93: 30 | E93: =+'LISTA MAESTRA'!D115 -> 30.666667 | F93: =+E93*D93 -> 920
B94: PASTA DE AJO | C94: GR | F94: =+E94*D94 -> 0
B95: CREMA DE LECHE | C95: GR | D95: 100 | E95: =+'LISTA MAESTRA'!D73 -> 20.229885 | F95: =+E95*D95 -> 2022.9885
B96: PEREJIL | C96: GR | F96: =+E96*D96 -> 0
A98: COSTO TOTAL DE LOS INGREDIENTES | F98: =SUM(F86:F97) -> 18707.759
A99: MARGEN DE ERROR O VARIACIÓN | E99: 0 | F99: =+F98*E99 -> 0
A100: COSTO TOTAL DE LA PREPARACIÓN + MARGEN DE ERROR | F100: =+F98+F99 -> 18707.759
A101: COSTO DE UNA PORCIÓN SUMANDO EL MARGEN DE ERROR | F101: =+F100/F84 -> 18707.759
A102: % COSTO MATERIA PRIMA ESTABLECIDO POR GERENCIA | F102: 0.35
A103: PRECIO POTENCIAL DE VENTA DE UNA PORCIÓN | F103: =+F101/F102 -> 53450.741
A104: PRECIO REAL DE VENTA DE UNA PORCIÓN | F104: =ROUNDUP(F103,-2) -> 53500
A105: % REAL DE COSTO (COSTO PORCIÓN SOBRE PRECIO REAL VENTA) | F105: =+F101/F104 -> 0.34967774
A106: IVA GENERADO AL VENDER CADA PORCIÓN | E106: 0.08 | F106: =+F104*E106 -> 4280
A107: PRECIO PARA LA CARTA DE CADA PORCIÓN | F107: =+F104+F106 -> 57780
A109: TRUCHA EN SALSA DE ALMENDRAS
A110: RECETAS ESTANDAR ALMA RURAL 2025
...

Sheet CARNE DEL CORRAL
A1: CHURRASCO DE RES
A2: RECETAS ESTANDAR ALMA RURAL 2025 | H2: LISTA MAESTRA | I2: 'RECETA BASE'
A3: : | E3: # RECETA | F3: 23
E4: # PORCIONES | F4: 1
A5: COD. | B5: INGREDIENTES | C5: UNID | D5: CANT. | E5: V/UNIT. | F5: V/TOTAL
B6: PORCION DE CHURRASCO 380 GR | C6: GR | D6: 380 | E6: =+'LISTA MAESTRA'!D7 -> 44 | F6: =+E6*D6 -> 16720
B7: PAPAS EN CASCO | C7: PORCION | D7: 1 | E7: =+'RECETA BASE'!F142 -> 2184.024 | F7: =+E7*D7 -> 2184.024
B8: ENSALADA FRESCA | C8: PORCION | D8: 1 | E8: =+'RECETA BASE'!F331 -> 1020.515 | F8: =+E8*D8 -> 1020.515
B9: ADOBO | C9: PORCION | D9: 1 | E9: =+'RECETA BASE'!F314 -> 558.18413 | F9: =+E9*D9 -> 558.18413
B10: CARBON | F10: =+E10*D10 -> 0
B11: SAL PARRILLERA | C11: GR | D11: 3 | E11: =+'LISTA MAESTRA'!D105 -> 28.157895 | F11: =+E11*D11 -> 84.473684
B12: SALSA DE ALIOLI | C12: PORCION | F12: =+E12*D12 -> 0
B13: SALSA DE UCHUVA | C13: PORCION | F13: =+E13*D13 -> 0
A15: COSTO TOTAL DE LOS INGREDIENTES | F15: =SUM(F6:F14) -> 20567.197
A16: MARGEN DE ERROR O VARIACIÓN | E16: 0 | F16: =+F15*E16 -> 0
A17: COSTO TOTAL DE LA PREPARACIÓN + MARGEN DE ERROR | F17: =+F15+F16 -> 20567.197
A18: COSTO DE UNA PORCIÓN SUMANDO EL MARGEN DE ERROR | F18: =+F17/F4 -> 20567.197
A19: % COSTO MATERIA PRIMA ESTABLECIDO POR GERENCIA | F19: 0.35
A20: PRECIO POTENCIAL DE VENTA DE UNA PORCIÓN | F20: =+F18/F19 -> 58763.419
A21: PRECIO REAL DE VENTA DE UNA PORCIÓN | F21: =ROUNDUP(F20,-2) -> 58800
A22: % REAL DE COSTO (COSTO PORCIÓN SOBRE PRECIO REAL VENTA) | F22: =+F18/F21 -> 0.34978226
A23: IVA GENERADO AL VENDER CADA PORCIÓN | E23: 0.08 | F23: =+F21*E23 -> 4704
A24: PRECIO PARA LA CARTA DE CADA PORCIÓN | F24: =+F21+F23 -> 63504
A27: PUNTA DE ANCA ASADA
A28: RECETAS ESTANDAR ALMA RURAL 2025
A29: : | E29: # RECETA | F29: 24
E30: # PORCIONES | F30: 1
A31: COD. | B31: INGREDIENTES | C31: UNID | D31: CANT. | E31: V/UNIT. | F31: V/TOTAL
B32: PORCION DE PUNTA DE ANCA 380 GR | C32: PORCION | D32: 380 | E32: =+'LISTA MAESTRA'!D6 -> 48.8 | F32: =E32*D32 -> 18544
B33: PORCION DE ENSALADA | C33: PORCION | D33: 1 | E33: =+'RECETA BASE'!F332 -> 962.75 | F33: =E33*D33 -> 962.75
B34: PAPAS EN CASCO | C34: PORCION | D34: 1 | E34: =+'RECETA BASE'!F142 -> 2184.024 | F34: =E34*D34 -> 2184.024
B35: ADOBO | C35: GR | D35: 1 | E35: =+'RECETA BASE'!F314 -> 558.18413 | F35: =E35*D35 -> 558.18413
B36: CARBON | F36: =E36*D36 -> 0
B37: SAL PARRILLERA | C37: GR | D37: 3 | E37: =+'LISTA MAESTRA'!D105 -> 28.157895 | F37: =E37*D37 -> 84.473684
B38: SALSA DE ALIOLI | C38: PORCION | F38: =E38*D38 -> 0
B39: SALSA DE UCHUVA | C39: PORCION | F39: =E39*D39 -> 0
A40: COSTO TOTAL DE LOS INGREDIENTES | F40: =SUM(F32:F39) -> 22333.432
A41: MARGEN DE ERROR O VARIACIÓN | E41: 0 | F41: =+F40*E41 -> 0
A42: COSTO TOTAL DE LA PREPARACIÓN + MARGEN DE ERROR | F42: =+F40+F41 -> 22333.432
A43: COSTO DE UNA PORCIÓN SUMANDO EL MARGEN DE ERROR | F43: =+F42/F30 -> 22333.432
A44: % COSTO MATERIA PRIMA ESTABLECIDO POR GERENCIA | F44: 0.35
A45: PRECIO POTENCIAL DE VENTA DE UNA PORCIÓN | F45: =+F43/F44 -> 63809.805
A46: PRECIO REAL DE VENTA DE UNA PORCIÓN | F46: =ROUNDUP(F45,-2) -> 63900
A47: % REAL DE COSTO (COSTO PORCIÓN SOBRE PRECIO REAL VENTA) | F47: =+F43/F46 -> 0.34950598
A48: IVA GENERADO AL VENDER CADA PORCIÓN | E48: 0.08 | F48: =+F46*E48 -> 5112
A49: PRECIO PARA LA CARTA DE CADA PORCIÓN | F49: =+F46+F48 -> 69012
A52: CORDERO AHUMADO
A53: RECETAS ESTANDAR ALMA RURAL 2025
A54: : | E54: # RECETA | F54: 25
E55: # PORCIONES | F55: 1
A56: COD. | B56: INGREDIENTES | C56: UNID | D56: CANT. | E56: V/UNIT. | F56: V/TOTAL
B57: RACK DE COSTILLAS DE CORDERO | C57: PORCIÓN | F57: =+E57*D57 -> 0
B58: MARINADA | C58: PORCION | D58: 1 | E58: =+'RECETA BASE'!F272 -> 1520.4375 | F58: =+E58*D58 -> 1520.4375
B59: PORCION DE ENSALADA | C59: PORCION | D59: 1 | E59: =+'RECETA BASE'!F331 -> 1020.515 | F59: =+E59*D59 -> 1020.515
B60: PAPAS EN CASCO | C60: PORCION | D60: 1 | E60: =+'RECETA BASE'!F142 -> 2184.024 | F60: =+E60*D60 -> 2184.024
B61: SAL PARRILLERA | C61: GR | D61: 10 | E61: =+'LISTA MAESTRA'!D105 -> 28.157895 | F61: =+E61*D61 -> 281.57895
B62: SALSA DE ALIOLI | C62: PORCION | F62: =+E62*D62 -> 0
B63: SALSA DE UCHUVA | C63: PORCION | F63: =+E63*D63 -> 0
A68: COSTO TOTAL DE LOS INGREDIENTES | F68: =SUM(F57:F67) -> 5006.5554
A69: MARGEN DE ERROR O VARIACIÓN | E69: 0 | F69: =+F68*E69 -> 0
A70: COSTO TOTAL DE LA PREPARACIÓN + MARGEN DE ERROR | F70: =+F68+F69 -> 5006.5554
A71: COSTO DE UNA PORCIÓN SUMANDO EL MARGEN DE ERROR | F71: =+F70/F55 -> 5006.5554
A72: % COSTO MATERIA PRIMA ESTABLECIDO POR GERENCIA | F72: 0.3
A73: PRECIO POTENCIAL DE VENTA DE UNA PORCIÓN | F73: =+F71/F72 -> 16688.518
A74: PRECIO REAL DE VENTA DE UNA PORCIÓN | F74: =ROUNDUP(F73,-2) -> 16700
A75: % REAL DE COSTO (COSTO PORCIÓN SOBRE PRECIO REAL VENTA) | F75: =+F71/F74 -> 0.29979374
A76: IVA GENERADO AL VENDER CADA PORCIÓN | E76: 0.08 | F76: =+F74*E76 -> 1336
A77: PRECIO PARA LA CARTA DE CADA PORCIÓN | F77: =+F74+F76 -> 18036
A79: HAMBURGUESA ARTESANAL DE LA CASA
A80: RECETAS ESTANDAR ALMA RURAL 2025
A81: : | E81: # RECETA | F81: 26
E82: # PORCIONES | F82: 1
A83: COD. | B83: INGREDIENTES | C83: UNID | D83: CANT. | E83: V/UNIT. | F83: V/TOTAL
B84: PORCION DE CARNE DE RES 170 GR | C84: PORCION | D84: 1 | E84: =+'RECETA BASE'!F406 -> 3753.8535 | F84: =+E84*D84 -> 3753.8535
B85: PORCION DE PAN | C85: PORCION | F85: =+E85*D85 -> 0
B86: PORCION DE PAPAS | C86: PORCION | D86: 1 | E86: =+'RECETA BASE'!F142 -> 2184.024 | F86: =+E86*D86 -> 2184.024
B87: LECHUGA CRESPA | C87: GR | D87: 10 | E87: =+'LISTA MAESTRA'!D36 -> 8.8 | F87: =+E87*D87 -> 88
B88: TOMATE CHONTO | C88: GR | D88: 50 | E88: =+'LISTA MAESTRA'!D46 -> 3.2 | F88: =+E88*D88 -> 160
B89: REPOLLO ENCURTIDO | C89: PORCION | D89: 1 | E89: =+'RECETA BASE'!F348 -> 408.75 | F89: =+E89*D89 -> 408.75
B90: TAJADA DE QUESO CRIOLLO 100 GR APR | C90: GR | D90: 100 | E90: =+'LISTA MAESTRA'!D74 -> 23.4 | F90: =+E90*D90 -> 2340
B91: TOCINETA | C91: UND | D91: 2 | E91: =+'LISTA MAESTRA'!D27 -> 660 | F91: =+E91*D91 -> 1320
B92: PEPINILLOS | C92: GR | D92: 10 | E92: =+'LISTA MAESTRA'!D81 -> 24.4 | F92: =+E92*D92 -> 244
F93: =+E93*D93 -> 0
A94: COSTO TOTAL DE LOS INGREDIENTES | F94: =SUM(F84:F93) -> 10498.627
A95: MARGEN DE ERROR O VARIACIÓN | E95: 0 | F95: =+F94*E95 -> 0
A96: COSTO TOTAL DE LA PREPARACIÓN + MARGEN DE ERROR | F96: =+F94+F95 -> 10498.627
A97: COSTO DE UNA PORCIÓN SUMANDO EL MARGEN DE ERROR | F97: =+F96/F82 -> 10498.627
A98: % COSTO MATERIA PRIMA ESTABLECIDO POR GERENCIA | F98: 0.35
A99: PRECIO POTENCIAL DE VENTA DE UNA PORCIÓN | F99: =+F97/F98 -> 29996.079
A100: PRECIO REAL DE VENTA DE UNA PORCIÓN | F100: =ROUNDUP(F99,-2) -> 30000
A101: % REAL DE COSTO (COSTO PORCIÓN SOBRE PRECIO REAL VENTA) | F101: =+F97/F100 -> 0.34995425
A102: IVA GENERADO AL VENDER CADA PORCIÓN | E102: 0.08 | F102: =+F100*E102 -> 2400
A103: PRECIO PARA LA CARTA DE CADA PORCIÓN | F103: =+F100+F102 -> 32400
A105: HAMBURGUESA ANGUS PREMIUM
A106: RECETAS ESTANDAR ALMA RURAL 2025
A107: : | E107: # RECETA | F107: 27
E108: # PORCIONES | F108: 1
A109: COD. | B109: INGREDIENTES | C109: UNID | D109: CANT. | E109: V/UNIT. | F109: V/TOTAL
B110: CARNE DE ANGUS HAMBURUGESA | C110: PORCION | D110: 1 | F110: =+E110*D110 -> 0
B111: PORCION DE PAN | C111: PORCION | F111: =+E111*D111 -> 0
...

Sheet VEGETARIANOS
A1: RAVIOLIS DE CHAMPIÑONES | P1: PROCEDIMIENTO
A2: RECETAS ESTANDAR ALMA RURAL 2025 | H2: LISTA MAESTRA | I2: 'RECETA BASE'
A3: : | E3: # RECETA | F3: 1
E4: # PORCIONES | F4: 1
A5: COD. | B5: INGREDIENTES | C5: UNID | D5: CANT. | E5: V/UNIT. | F5: V/TOTAL
B6: PORCION DE CHAMPIÑON | C6: PORCION | D6: 1 | E6: =+'RECETA BASE'!F202 -> 3239.793 | F6: =+E6*D6 -> 3239.793
B7: HARINA DE TRIGO | C7: GR | D7: 400 | E7: =+'LISTA MAESTRA'!D96 -> 3.4 | F7: =+E7*D7 -> 1360
B8: ACEITE DE OLIVA | C8: GR | D8: 60 | E8: =+'LISTA MAESTRA'!D123 -> 30.5 | F8: =+E8*D8 -> 1830
B9: HUEVOS | C9: UND | D9: 4 | E9: =+'LISTA MAESTRA'!D39 -> 433.33333 | F9: =+E9*D9 -> 1733.3333
F10: =+E10*D10 -> 0
F11: =+E11*D11 -> 0
F12: =+E12*D12 -> 0
F13: =+E13*D13 -> 0
F14: =+E14*D14 -> 0
A15: COSTO TOTAL DE LOS INGREDIENTES | F15: =SUM(F6:F14) -> 8163.1263
A16: MARGEN DE ERROR O VARIACIÓN | E16: 0 | F16: =+F15*E16 -> 0
A17: COSTO TOTAL DE LA PREPARACIÓN + MARGEN DE ERROR | F17: =+F15+F16 -> 8163.1263
A18: COSTO DE UNA PORCIÓN SUMANDO EL MARGEN DE ERROR | F18: =+F17/F4 -> 8163.1263
A19: % COSTO MATERIA PRIMA ESTABLECIDO POR GERENCIA | F19: 0.35
A20: PRECIO POTENCIAL DE VENTA DE UNA PORCIÓN | F20: =+F18/F19 -> 23323.218
A21: PRECIO REAL DE VENTA DE UNA PORCIÓN | F21: =ROUNDUP(F20,-2) -> 23400
A22: % REAL DE COSTO (COSTO PORCIÓN SOBRE PRECIO REAL VENTA) | F22: =+F18/F21 -> 0.34885155
A23: IVA GENERADO AL VENDER CADA PORCIÓN | E23: 0.08 | F23: =+F21*E23 -> 1872
A24: PRECIO PARA LA CARTA DE CADA PORCIÓN | F24: =+F21+F23 -> 25272
A27: BOWL VEGANO | P27: PROCEDIMIENTO
A28: RECETAS ESTANDAR ALMA RURAL 2025
A29: : | E29: # RECETA | F29: 1
E30: # PORCIONES | F30: 1
A31: COD. | B31: INGREDIENTES | C31: UNID | D31: CANT. | E31: V/UNIT. | F31: V/TOTAL
B32: ZANAHORIA | C32: GR | D32: 100 | E32: =+'LISTA MAESTRA'!D56 -> 5.9 | F32: =E32*D32 -> 590
B33: PIMENTON | C33: GR | D33: 100 | E33: =+'LISTA MAESTRA'!D60 -> 10.6 | F33: =E33*D33 -> 1060
B34: BROCOLI | C34: GR | D34: 100 | E34: =+'LISTA MAESTRA'!D124 -> 5.6
B35: CHAMPIÑON | C35: GR | D35: 100 | E35: =+'LISTA MAESTRA'!D40 -> 29.6 | F35: =E35*D35 -> 2960
B36: CHERRY | C36: GR | D36: 100 | F36: =E36*D36 -> 0
A38: COSTO TOTAL DE LOS INGREDIENTES | F38: =SUM(F32:F37) -> 4610
A39: MARGEN DE ERROR O VARIACIÓN | E39: 0 | F39: =+F38*E39 -> 0
A40: COSTO TOTAL DE LA PREPARACIÓN + MARGEN DE ERROR | F40: =+F38+F39 -> 4610
A41: COSTO DE UNA PORCIÓN SUMANDO EL MARGEN DE ERROR | F41: =+F40/F30 -> 4610
A42: % COSTO MATERIA PRIMA ESTABLECIDO POR GERENCIA | F42: 0.35
A43: PRECIO POTENCIAL DE VENTA DE UNA PORCIÓN | F43: =+F41/F42 -> 13171.429
A44: PRECIO REAL DE VENTA DE UNA PORCIÓN | F44: =ROUNDUP(F43,-2) -> 13200
A45: % REAL DE COSTO (COSTO PORCIÓN SOBRE PRECIO REAL VENTA) | F45: =+F41/F44 -> 0.34924242
A46: IVA GENERADO AL VENDER CADA PORCIÓN | E46: 0.08 | F46: =+F44*E46 -> 1056
A47: PRECIO PARA LA CARTA DE CADA PORCIÓN | F47: =+F44+F46 -> 14256
A50: POLLO INFANTIL | P50: PROCEDIMIENTO
A51: RECETAS ESTANDAR ALMA RURAL 2025
A52: : | E52: # RECETA | F52: 3
E53: # PORCIONES | F53: 1
A54: COD. | B54: INGREDIENTES | C54: UNID | D54: CANT. | E54: V/UNIT. | F54: V/TOTAL
B55: PECHUGA DE POLLO | C55: GR | D55: 200 | E55: =+'LISTA MAESTRA'!D30 -> 23.4 | F55: =+E55*D55 -> 4680
B56: PORCION DE PAPAS | C56: PORCION | D56: 1 | E56: =+'RECETA BASE'!F142 -> 2184.024 | F56: =+E56*D56 -> 2184.024
B57: QUINUA | C57: GR | D57: 80 | E57: =+'LISTA MAESTRA'!D94 -> 33.8 | F57: =+E57*D57 -> 2704
B58: ADOBO | C58: PORCION | D58: 1 | E58: =+'RECETA BASE'!F314 -> 558.18413 | F58: =+E58*D58 -> 558.18413
A60: COSTO TOTAL DE LOS INGREDIENTES | F60: =SUM(F55:F59) -> 10126.208
A61: MARGEN DE ERROR O VARIACIÓN | E61: 0 | F61: =+F60*E61 -> 0
A62: COSTO TOTAL DE LA PREPARACIÓN + MARGEN DE ERROR | F62: =+F60+F61 -> 10126.208
A63: COSTO DE UNA PORCIÓN SUMANDO EL MARGEN DE ERROR | F63: =+F62/F53 -> 10126.208
A64: % COSTO MATERIA PRIMA ESTABLECIDO POR GERENCIA | F64: 0.35
A65: PRECIO POTENCIAL DE VENTA DE UNA PORCIÓN | F65: =+F63/F64 -> 28932.023
A66: PRECIO REAL DE VENTA DE UNA PORCIÓN | F66: =ROUNDUP(F65,-2) -> 29000
A67: % REAL DE COSTO (COSTO PORCIÓN SOBRE PRECIO REAL VENTA) | F67: =+F63/F66 -> 0.34917959
A68: IVA GENERADO AL VENDER CADA PORCIÓN | E68: 0.08 | F68: =+F66*E68 -> 2320
A69: PRECIO PARA LA CARTA DE CADA PORCIÓN | F69: =+F66+F68 -> 31320

Sheet PRESUPUESTO
B2: COSTOS OPERATIVOS COCINA | J2: ITEM
B3: NOMBRE DEL PUNTO | D3: CAFETERIA 1 | F3: PRESUPUESTO | G3: PORCENTAJE | I3: AUX | J3: 550000 | K3: V
B4: COSTOS FIJO | F4: ARRIENDO | G4: =+C5/C19 -> 0.3818182 | I4: AXU COCINA | J4: 540000
B5: ARRIENDO | C5: 1200000 | F5: NOMINA | G5: =+C6/C19 -> 0.73500003 | I5: FRITURAS | J5: 220000
B6: NOMINA | C6: =+J10 -> 2310000 | F6: SERVICIOS | G6: =+SUM(C7+C10+C11+C12)/C19 -> 0.21954546 | I6: STEWARD | J6: 200000
B7: INTERNET | F7: MATERIA PRIMA | G7: 0.4 | I7: MESERO SABADO | J7: 400000
F8: UTILIDAD BRUTA (ingresos - costos) | G8: =+C21/C19 -> -0.97272736 | I8: MESERO DOMINGO 1 | J8: 200000
B9: COSTOS VARIABLES | G9: =SUM(G4:G8) -> 0.76363633 | I9: MESERO DOMINGO 2 | J9: 200000
B10: LUZ | C10: 500000 | J10: =SUM(J3:J9) -> 2310000
B11: AGUA
B12: GAS | C12: 190000 | I12: INVERSIÓN TOTAL
B13: MATERIA PRIMA | C13: 2000000 | F13: PROYECCIÓN VENTA MENSUAL | G13: =+C17 -> 6200000 | I13: MESES
B14: GASTOS OPERATIVOS | I14: CUOTA MENSUAL | J14: =+J12/J13 -> #DIV/0!
B15: RECUPERACIÓN DE LA INVERSIÓN MENSUAL
B17: TOTAL COSTOS OPERATIVOS (fijos y variables) | C17: =+SUM(C5+C6+C7+C10+C11+C12+C13+C16) -> 6200000 | G17: =+G14*8 -> 0
B18: VENTAS MENSUALES
C19: 3142857
F20: =+C13/G7 -> 5000000
B21: DIFERENCIA | C21: =+C19-C17 -> -3057143

Sheet SALSA DE AJO
B2: PROCEDIMIENTO SALSA DE AJO
B3: Preparación con Licuadora Prepara los ingredientes: Pela los dientes de ajo por la mitad y saca el germen para reducir el amargo del ajo Combina los ingredientes base: En el vaso de la licuadora, añade el huevo, la mostaza, el ajo, la sal y la pimienta. Inicia el licuado: Coloca la tapa de la licuadora, asegurándote de que la abertura superior para verter esté abierta. Enciende la licuadora a velocidad media-baja para empezar a mezclar los ingredientes. Añade el aceite lentamente: Con la licuadora funcionando, comienza a verter el aceite en un chorro muy fino y constante a través de la abertura de la tapa. Es crucial que lo hagas lentamente para que la mezcla emulsione correctamente. Observa la consistencia: Continúa vertiendo el aceite hasta que la salsa comience a espesarse y adquiera la consistencia deseada. Si notas que se está volviendo demasiado espesa, puedes detenerte antes de usar todo el aceite. Si la quieres más líquida, puedes añadir un poco de agua o leche al final. yo recomiendo crema de leche. Prueba y ajusta: Una vez que la salsa esté lista, detén la licuadora, pruébala y ajusta la sal o la pimienta si es necesario. Si quieres más sabor a ajo, puedes triturar un diente de ajo extra en un mortero y agregarlo a la salsa ya terminada. Consejos Adicionales Temperatura: , es mejor si todos los ingredientes están a temperatura ambiente para una mejor emulsión. Velocidad: Es importante comenzar con una velocidad baja para que la mezcla se combine bien antes de aumentar la velocidad. Volumen: Un litro es una cantidad grande para una licuadora doméstica. Asegúrate de que el vaso de tu licuadora tenga la capacidad suficiente. Si no es así, puedes hacer la receta en dos tandas.

Sheet REDUCCIÓN BALSAMICO
B2: PROCEDIMIENTO BALSAMICO
B3: Paso a Paso para la Reducción Combina los ingredientes: Vierte el vinagre balsámico en una olla o sartén antiadherente de fondo grueso. Azúcar, añádela ahora y revuelve hasta que se disuelva. Lleva a ebullición: Calienta la mezcla a fuego medio-alto hasta que comience a hervir. Reduce el fuego y cocina a fuego lento: Una vez que hierva, baja el fuego a medio-bajo. La mezcla debe mantenerse en un hervor suave y constante. No la tapes. Monitorea la reducción: Este es el paso más importante. El proceso puede tomar entre 15 y 30 minutos, dependiendo del tamaño de la olla y la intensidad del fuego. Observa la consistencia: Al principio se verá muy líquida. A medida que el líquido se evapore, la consistencia cambiará. cuando la preparación no este acida agregar un gramo de cmc para mejorar la consistencia. Haz la prueba de la cuchara: Saca una cuchara y sumérgela en la reducción. Si la retiras y la reducción cubre la parte de atrás de la cuchara sin gotear rápidamente, está lista. Ten cuidado de no sobre-reducir: La reducción de vinagre balsámico se volverá mucho más espesa una vez que se enfríe. Es mejor retirarla del fuego un poco antes de lo que crees que está lista. Retira del fuego y enfría: Quita la olla del calor. . Deja que la reducción se enfríe completamente antes de almacenarla. Al enfriarse, se espesará hasta alcanzar la consistencia de un jarabe. Almacena: Vierte la reducción en una botella o recipiente hermético. Guárdala en un lugar fresco y oscuro, como una despensa. No es necesario refrigerarla.

Sheet MIEL DE JENGIBRE
B2: MIEL DE GENGIBRE
B3: EN LA MIEL AGREGAR EL GENGIBRE Y EL LIMONCILLO Y DEJAR REPOSAR POR 3 DIAS, EL GENGIBRE SE DEBE AGREGAR SIN PIEL

Sheet DE LA CASA
B2: SALSA DE LA CASA
B3: Procedimiento (Paso a Paso) Prepara los ingredientes secos: En un tazón mediano, mezcla el ajo en polvo, las dos pimientas y la páprika. Revolver bien te ayudará a evitar grumos. Combina la base líquida: En un recipiente grande (o en el vaso de una licuadora), agrega la mayonesa, la salsa de tomate y la salsa inglesa. Integra todos los ingredientes: Añade la mezcla de especias secas al recipiente con los ingredientes húmedos. Mezcla hasta homogeneizar: Con la ayuda de, una licuadora, mezcla todos los ingredientes hasta obtener una salsa de color uniforme y sin grumos. Prueba y ajusta: Una vez que la salsa esté bien mezclada, pruébala. Puedes ajustar la cantidad de cada ingrediente según tus preferencias personales. Por ejemplo, si la quieres más dulce, agrega un poco más de salsa de tomate; si buscas un sabor más profundo y salado, añade más salsa inglesa. Notas Adicionales Consistencia: La mayonesa es la que define la consistencia de esta salsa. Si quieres una salsa más líquida, puedes agregar un poco de agua o leche al gusto. Almacenamiento: Vierte la salsa en un recipiente hermético. Esta salsa se conserva bien refrigerada por 5 a 7 días. Variantes: Puedes usar páprika ahumada para darle un toque diferente o añadir un poco de cebolla en polvo para un sabor más complejo.
